{
  "subject": "english",
  "curriculum": "cam",
  "stage": "primary",
  "name_zh": "剑桥 Primary · 英语",
  "name_en": "Cambridge Primary English",
  "description": "Cambridge Primary English curriculum for ages 5-11. Strands: Reading, Writing, Speaking & Listening, Phonics, Grammar & Vocabulary.",
  "source": "https://www.cambridgeinternational.org/programmes-and-qualifications/cambridge-primary/curriculum/",
  "domains": [
    {
      "name": "阅读 / Reading / Reading",
      "name_en": "Reading",
      "nodes": [
        {
          "id": "english-cam-primary-phonics",
          "name": "自然拼读",
          "name_en": "Phonics",
          "grade": 1,
          "difficulty": 1,
          "status": "placeholder",
          "prerequisites": [],
          "courses": [],
          "extends": [],
          "parallel": []
        },
        {
          "id": "english-cam-primary-sight-words",
          "name": "高频词识别",
          "name_en": "Sight words",
          "grade": 1,
          "difficulty": 1,
          "status": "placeholder",
          "prerequisites": [
            "english-cam-primary-phonics"
          ],
          "courses": [],
          "extends": [],
          "parallel": []
        },
        {
          "id": "english-cam-primary-reading-fluency",
          "name": "阅读流利度",
          "name_en": "Reading fluency",
          "grade": 3,
          "difficulty": 2,
          "status": "placeholder",
          "prerequisites": [
            "english-cam-primary-sight-words"
          ],
          "courses": [],
          "extends": [],
          "parallel": []
        },
        {
          "id": "english-cam-primary-comprehension",
          "name": "阅读理解",
          "name_en": "Reading comprehension",
          "grade": 4,
          "difficulty": 2,
          "status": "placeholder",
          "prerequisites": [
            "english-cam-primary-reading-fluency"
          ],
          "courses": [],
          "extends": [],
          "parallel": []
        },
        {
          "id": "english-cam-primary-inference-primary",
          "name": "推断理解",
          "name_en": "Inference",
          "grade": 5,
          "difficulty": 3,
          "status": "placeholder",
          "prerequisites": [
            "english-cam-primary-comprehension"
          ],
          "courses": [],
          "extends": [],
          "parallel": []
        },
        {
          "id": "english-cam-primary-text-types",
          "name": "文本类型辨识",
          "name_en": "Text types",
          "grade": 4,
          "difficulty": 2,
          "status": "placeholder",
          "prerequisites": [
            "english-cam-primary-comprehension"
          ],
          "courses": [],
          "extends": [],
          "parallel": []
        }
      ],
      "color": "#06b6d4"
    },
    {
      "name": "写作 / Writing / Writing",
      "name_en": "Writing",
      "nodes": [
        {
          "id": "english-cam-primary-handwriting",
          "name": "写字与书写",
          "name_en": "Handwriting",
          "grade": 1,
          "difficulty": 1,
          "status": "placeholder",
          "prerequisites": [],
          "courses": [],
          "extends": [],
          "parallel": []
        },
        {
          "id": "english-cam-primary-sentence-writing",
          "name": "句子写作",
          "name_en": "Sentence writing",
          "grade": 2,
          "difficulty": 2,
          "status": "placeholder",
          "prerequisites": [
            "english-cam-primary-handwriting"
          ],
          "courses": [],
          "extends": [],
          "parallel": []
        },
        {
          "id": "english-cam-primary-paragraph",
          "name": "段落写作",
          "name_en": "Paragraph writing",
          "grade": 4,
          "difficulty": 2,
          "status": "placeholder",
          "prerequisites": [
            "english-cam-primary-sentence-writing"
          ],
          "courses": [],
          "extends": [],
          "parallel": []
        },
        {
          "id": "english-cam-primary-narrative-primary",
          "name": "记叙文",
          "name_en": "Narrative writing",
          "grade": 4,
          "difficulty": 3,
          "status": "placeholder",
          "prerequisites": [
            "english-cam-primary-paragraph"
          ],
          "courses": [],
          "extends": [],
          "parallel": []
        },
        {
          "id": "english-cam-primary-descriptive-primary",
          "name": "描写文",
          "name_en": "Descriptive writing",
          "grade": 5,
          "difficulty": 3,
          "status": "placeholder",
          "prerequisites": [
            "english-cam-primary-paragraph"
          ],
          "courses": [],
          "extends": [],
          "parallel": []
        },
        {
          "id": "english-cam-primary-letter-writing",
          "name": "书信写作",
          "name_en": "Letter writing",
          "grade": 5,
          "difficulty": 3,
          "status": "placeholder",
          "prerequisites": [
            "english-cam-primary-paragraph"
          ],
          "courses": [],
          "extends": [],
          "parallel": []
        }
      ],
      "color": "#3b82f6"
    },
    {
      "name": "口语与聆听 / Speaking & Listening / Speaking & Listening",
      "name_en": "Speaking & Listening",
      "nodes": [
        {
          "id": "english-cam-primary-speaking-basics",
          "name": "口语基础",
          "name_en": "Speaking basics",
          "grade": 1,
          "difficulty": 1,
          "status": "placeholder",
          "prerequisites": [],
          "courses": [],
          "extends": [],
          "parallel": []
        },
        {
          "id": "english-cam-primary-group-discussion",
          "name": "小组讨论",
          "name_en": "Group discussion",
          "grade": 3,
          "difficulty": 2,
          "status": "placeholder",
          "prerequisites": [
            "english-cam-primary-speaking-basics"
          ],
          "courses": [],
          "extends": [],
          "parallel": []
        },
        {
          "id": "english-cam-primary-presentation-primary",
          "name": "口头表达",
          "name_en": "Oral presentation",
          "grade": 5,
          "difficulty": 3,
          "status": "placeholder",
          "prerequisites": [
            "english-cam-primary-group-discussion"
          ],
          "courses": [],
          "extends": [],
          "parallel": []
        }
      ],
      "color": "#8b5cf6"
    },
    {
      "name": "语法与词汇 / Grammar & Vocabulary / Grammar & Vocabulary",
      "name_en": "Grammar & Vocabulary",
      "nodes": [
        {
          "id": "english-cam-primary-parts-of-speech",
          "name": "词性入门",
          "name_en": "Parts of speech",
          "grade": 2,
          "difficulty": 2,
          "status": "placeholder",
          "prerequisites": [],
          "courses": [],
          "extends": [],
          "parallel": []
        },
        {
          "id": "english-cam-primary-tenses-primary",
          "name": "时态（一般/进行/完成）",
          "name_en": "Tenses",
          "grade": 4,
          "difficulty": 3,
          "status": "placeholder",
          "prerequisites": [
            "english-cam-primary-parts-of-speech"
          ],
          "courses": [],
          "extends": [],
          "parallel": []
        },
        {
          "id": "english-cam-primary-punctuation",
          "name": "标点符号",
          "name_en": "Punctuation",
          "grade": 3,
          "difficulty": 2,
          "status": "placeholder",
          "prerequisites": [
            "english-cam-primary-sentence-writing"
          ],
          "courses": [],
          "extends": [],
          "parallel": []
        },
        {
          "id": "english-cam-primary-vocabulary-building",
          "name": "词汇拓展",
          "name_en": "Vocabulary building",
          "grade": 4,
          "difficulty": 2,
          "status": "placeholder",
          "prerequisites": [],
          "courses": [],
          "extends": [],
          "parallel": []
        },
        {
          "id": "english-cam-primary-spelling-rules",
          "name": "拼写规则",
          "name_en": "Spelling rules",
          "grade": 3,
          "difficulty": 2,
          "status": "placeholder",
          "prerequisites": [
            "english-cam-primary-phonics"
          ],
          "courses": [],
          "extends": [],
          "parallel": []
        }
      ],
      "color": "#ec4899"
    }
  ]
}