{
  "subject": "english",
  "curriculum": "cam-primary",
  "stage": "p",
  "name_zh": "剑桥小学 · 英语",
  "name_en": "Cambridge Primary English",
  "description": "Cambridge Primary English curriculum framework (Stages 1-6).",
  "source": "https://www.cambridgeinternational.org/programmes-and-qualifications/cambridge-primary/cambridge-primary-curriculum/",
  "domains": [
    {
      "name": "听力 Listening / Listening",
      "name_en": "Listening",
      "nodes": [
        {
          "id": "english-cam-primary-p-listen-sounds",
          "name": "辨音听力",
          "name_en": "Phonemic awareness",
          "grade": 1,
          "difficulty": 1,
          "status": "placeholder",
          "prerequisites": [],
          "courses": [],
          "extends": [],
          "parallel": []
        },
        {
          "id": "english-cam-primary-p-listen-stories",
          "name": "听故事",
          "name_en": "Listening to stories",
          "grade": 2,
          "difficulty": 2,
          "status": "placeholder",
          "prerequisites": [
            "english-cam-primary-p-listen-sounds"
          ],
          "courses": [],
          "extends": [],
          "parallel": []
        },
        {
          "id": "english-cam-primary-p-listen-details",
          "name": "细节理解",
          "name_en": "Detailed listening",
          "grade": 4,
          "difficulty": 3,
          "status": "placeholder",
          "prerequisites": [
            "english-cam-primary-p-listen-stories"
          ],
          "courses": [],
          "extends": [],
          "parallel": []
        }
      ]
    },
    {
      "name": "口语 Speaking / Speaking",
      "name_en": "Speaking",
      "nodes": [
        {
          "id": "english-cam-primary-p-speaking-basic",
          "name": "基础口语",
          "name_en": "Basic speaking",
          "grade": 1,
          "difficulty": 1,
          "status": "placeholder",
          "prerequisites": [],
          "courses": [],
          "extends": [],
          "parallel": []
        },
        {
          "id": "english-cam-primary-p-presentation-p",
          "name": "简单演讲",
          "name_en": "Simple presentation",
          "grade": 4,
          "difficulty": 3,
          "status": "placeholder",
          "prerequisites": [
            "english-cam-primary-p-speaking-basic"
          ],
          "courses": [],
          "extends": [],
          "parallel": []
        }
      ]
    },
    {
      "name": "阅读 Reading / Reading",
      "name_en": "Reading",
      "nodes": [
        {
          "id": "english-cam-primary-p-phonics",
          "name": "拼读规则",
          "name_en": "Phonics",
          "grade": 1,
          "difficulty": 1,
          "status": "placeholder",
          "prerequisites": [],
          "courses": [],
          "extends": [],
          "parallel": []
        },
        {
          "id": "english-cam-primary-p-fluency",
          "name": "阅读流畅度",
          "name_en": "Reading fluency",
          "grade": 3,
          "difficulty": 2,
          "status": "placeholder",
          "prerequisites": [
            "english-cam-primary-p-phonics"
          ],
          "courses": [],
          "extends": [],
          "parallel": []
        },
        {
          "id": "english-cam-primary-p-comprehension-p",
          "name": "阅读理解",
          "name_en": "Comprehension",
          "grade": 5,
          "difficulty": 3,
          "status": "placeholder",
          "prerequisites": [
            "english-cam-primary-p-fluency"
          ],
          "courses": [],
          "extends": [],
          "parallel": []
        }
      ]
    },
    {
      "name": "写作 Writing / Writing",
      "name_en": "Writing",
      "nodes": [
        {
          "id": "english-cam-primary-p-handwriting",
          "name": "书法",
          "name_en": "Handwriting",
          "grade": 1,
          "difficulty": 1,
          "status": "placeholder",
          "prerequisites": [],
          "courses": [],
          "extends": [],
          "parallel": []
        },
        {
          "id": "english-cam-primary-p-sentence-construct",
          "name": "句子构造",
          "name_en": "Sentence construction",
          "grade": 3,
          "difficulty": 2,
          "status": "placeholder",
          "prerequisites": [
            "english-cam-primary-p-handwriting"
          ],
          "courses": [],
          "extends": [],
          "parallel": []
        },
        {
          "id": "english-cam-primary-p-paragraphs",
          "name": "段落写作",
          "name_en": "Paragraph writing",
          "grade": 5,
          "difficulty": 3,
          "status": "placeholder",
          "prerequisites": [
            "english-cam-primary-p-sentence-construct"
          ],
          "courses": [],
          "extends": [],
          "parallel": []
        }
      ]
    }
  ]
}