{
  "subject": "english",
  "curriculum": "us",
  "stage": "hs",
  "name_zh": "美式 HS · 英语语文",
  "name_en": "US HS English Language Arts (CCSS)",
  "description": "CCSS ELA 9-12. Reading Literature, Reading Informational Text, Writing, Speaking & Listening, Language. College & Career Ready standards.",
  "source": "https://www.thecorestandards.org/ELA-Literacy/",
  "domains": [
    {
      "name": "文学阅读 / Reading Literature / Reading Literature",
      "name_en": "Reading Literature",
      "nodes": [
        {
          "id": "english-us-hs-literary-analysis-hs",
          "name": "高级文学分析",
          "name_en": "Advanced literary analysis",
          "grade": 9,
          "difficulty": 4,
          "status": "placeholder",
          "prerequisites": [],
          "courses": [],
          "extends": [],
          "parallel": []
        },
        {
          "id": "english-us-hs-american-lit",
          "name": "美国文学",
          "name_en": "American literature",
          "grade": 10,
          "difficulty": 4,
          "status": "placeholder",
          "prerequisites": [
            "english-us-hs-literary-analysis-hs"
          ],
          "courses": [],
          "extends": [],
          "parallel": []
        },
        {
          "id": "english-us-hs-british-lit",
          "name": "英国文学",
          "name_en": "British literature",
          "grade": 11,
          "difficulty": 4,
          "status": "placeholder",
          "prerequisites": [
            "english-us-hs-literary-analysis-hs"
          ],
          "courses": [],
          "extends": [],
          "parallel": []
        },
        {
          "id": "english-us-hs-world-lit-hs",
          "name": "世界文学",
          "name_en": "World literature",
          "grade": 12,
          "difficulty": 4,
          "status": "placeholder",
          "prerequisites": [
            "english-us-hs-literary-analysis-hs"
          ],
          "courses": [],
          "extends": [],
          "parallel": []
        },
        {
          "id": "english-us-hs-shakespeare-hs",
          "name": "莎士比亚",
          "name_en": "Shakespeare",
          "grade": 10,
          "difficulty": 5,
          "status": "placeholder",
          "prerequisites": [
            "english-us-hs-literary-analysis-hs"
          ],
          "courses": [],
          "extends": [],
          "parallel": []
        },
        {
          "id": "english-us-hs-modern-novel",
          "name": "现代小说",
          "name_en": "Modern novels",
          "grade": 11,
          "difficulty": 4,
          "status": "placeholder",
          "prerequisites": [
            "english-us-hs-literary-analysis-hs"
          ],
          "courses": [],
          "extends": [],
          "parallel": []
        }
      ]
    },
    {
      "name": "信息性文本 / Reading Informational / Reading Informational",
      "name_en": "Reading Informational",
      "nodes": [
        {
          "id": "english-us-hs-argument-analysis-hs",
          "name": "论证分析",
          "name_en": "Argument analysis",
          "grade": 9,
          "difficulty": 4,
          "status": "placeholder",
          "prerequisites": [],
          "courses": [],
          "extends": [],
          "parallel": []
        },
        {
          "id": "english-us-hs-rhetoric-hs",
          "name": "修辞分析",
          "name_en": "Rhetorical analysis",
          "grade": 10,
          "difficulty": 5,
          "status": "placeholder",
          "prerequisites": [
            "english-us-hs-argument-analysis-hs"
          ],
          "courses": [],
          "extends": [],
          "parallel": []
        },
        {
          "id": "english-us-hs-synthesis",
          "name": "文献综合",
          "name_en": "Synthesis",
          "grade": 11,
          "difficulty": 5,
          "status": "placeholder",
          "prerequisites": [
            "english-us-hs-rhetoric-hs"
          ],
          "courses": [],
          "extends": [],
          "parallel": []
        },
        {
          "id": "english-us-hs-critical-evaluation-hs",
          "name": "批判性评估",
          "name_en": "Critical evaluation",
          "grade": 12,
          "difficulty": 5,
          "status": "placeholder",
          "prerequisites": [
            "english-us-hs-synthesis"
          ],
          "courses": [],
          "extends": [],
          "parallel": []
        }
      ]
    },
    {
      "name": "写作 / Writing / Writing",
      "name_en": "Writing",
      "nodes": [
        {
          "id": "english-us-hs-argumentative-hs",
          "name": "论证文写作",
          "name_en": "Argumentative writing",
          "grade": 9,
          "difficulty": 4,
          "status": "placeholder",
          "prerequisites": [],
          "courses": [],
          "extends": [],
          "parallel": []
        },
        {
          "id": "english-us-hs-informative-hs",
          "name": "说明文写作",
          "name_en": "Informative writing",
          "grade": 9,
          "difficulty": 4,
          "status": "placeholder",
          "prerequisites": [],
          "courses": [],
          "extends": [],
          "parallel": []
        },
        {
          "id": "english-us-hs-narrative-hs",
          "name": "叙事文",
          "name_en": "Narrative writing",
          "grade": 10,
          "difficulty": 4,
          "status": "placeholder",
          "prerequisites": [],
          "courses": [],
          "extends": [],
          "parallel": []
        },
        {
          "id": "english-us-hs-research-paper-hs",
          "name": "研究论文",
          "name_en": "Research paper",
          "grade": 11,
          "difficulty": 5,
          "status": "placeholder",
          "prerequisites": [
            "english-us-hs-argumentative-hs"
          ],
          "courses": [],
          "extends": [],
          "parallel": []
        },
        {
          "id": "english-us-hs-college-essay",
          "name": "大学申请文",
          "name_en": "College essay",
          "grade": 12,
          "difficulty": 4,
          "status": "placeholder",
          "prerequisites": [
            "english-us-hs-narrative-hs"
          ],
          "courses": [],
          "extends": [],
          "parallel": []
        }
      ]
    },
    {
      "name": "语言与口语 / Language & Speaking / Language & Speaking",
      "name_en": "Language & Speaking",
      "nodes": [
        {
          "id": "english-us-hs-vocabulary-hs",
          "name": "高级词汇",
          "name_en": "Advanced vocabulary",
          "grade": 9,
          "difficulty": 4,
          "status": "placeholder",
          "prerequisites": [],
          "courses": [],
          "extends": [],
          "parallel": []
        },
        {
          "id": "english-us-hs-grammar-style",
          "name": "语法与文风",
          "name_en": "Grammar & style",
          "grade": 10,
          "difficulty": 4,
          "status": "placeholder",
          "prerequisites": [
            "english-us-hs-vocabulary-hs"
          ],
          "courses": [],
          "extends": [],
          "parallel": []
        },
        {
          "id": "english-us-hs-formal-speech",
          "name": "正式演讲",
          "name_en": "Formal speech",
          "grade": 11,
          "difficulty": 4,
          "status": "placeholder",
          "prerequisites": [],
          "courses": [],
          "extends": [],
          "parallel": []
        },
        {
          "id": "english-us-hs-debate-hs",
          "name": "辩论",
          "name_en": "Debate",
          "grade": 12,
          "difficulty": 5,
          "status": "placeholder",
          "prerequisites": [
            "english-us-hs-formal-speech"
          ],
          "courses": [],
          "extends": [],
          "parallel": []
        }
      ]
    }
  ]
}