{
  "subject": "history",
  "name": "高中历史",
  "name_en": "High School History",
  "grade_range": [
    10,
    12
  ],
  "domains": [
    {
      "id": "ancient-china-h",
      "name": "中国古代史",
      "color": "#dc2626",
      "nodes": [
        {
          "id": "hist-h-ancient-civ",
          "name": "中华文明起源（史前·新石器）",
          "grade": 10,
          "prerequisites": [],
          "extends": [],
          "parallel": [],
          "courses": [],
          "status": "gap",
          "curriculum_points": [
            "高中10年级学段目标：理解并掌握「中华文明起源（史前·新石器）」的基本概念与方法",
            "学业要求：能在真实情境中识别、运用「中华文明起源（史前·新石器）」解决问题",
            "活动建议：通过观察、实验、练习、讨论等方式深化对「中华文明起源（史前·新石器）」的理解"
          ]
        },
        {
          "id": "hist-h-early-state",
          "name": "中华文明的起源与早期国家",
          "grade": 10,
          "prerequisites": [
            "hist-h-ancient-civ"
          ],
          "extends": [],
          "parallel": [],
          "courses": [],
          "status": "gap",
          "curriculum_points": [
            "高中10年级学段目标：理解并掌握「中华文明的起源与早期国家」的基本概念与方法",
            "学业要求：能在真实情境中识别、运用「中华文明的起源与早期国家」解决问题",
            "活动建议：通过观察、实验、练习、讨论等方式深化对「中华文明的起源与早期国家」的理解"
          ]
        },
        {
          "id": "hist-h-classical-civ",
          "name": "先秦（夏商周·春秋战国）",
          "grade": 10,
          "prerequisites": [
            "hist-h-early-state"
          ],
          "extends": [],
          "parallel": [],
          "courses": [
            "hist-classical-civilization"
          ],
          "status": "active",
          "curriculum_points": [
            "高中10年级学段目标：理解并掌握「先秦（夏商周·春秋战国）」的基本概念与方法",
            "学业要求：能在真实情境中识别、运用「先秦（夏商周·春秋战国）」解决问题",
            "活动建议：通过观察、实验、练习、讨论等方式深化对「先秦（夏商周·春秋战国）」的理解"
          ]
        },
        {
          "id": "hist-h-feudal-system",
          "name": "秦汉统一与中央集权制度",
          "grade": 10,
          "prerequisites": [
            "hist-h-classical-civ"
          ],
          "extends": [],
          "parallel": [],
          "courses": [],
          "status": "gap",
          "curriculum_points": [
            "高中10年级学段目标：理解并掌握「秦汉统一与中央集权制度」的基本概念与方法",
            "学业要求：能在真实情境中识别、运用「秦汉统一与中央集权制度」解决问题",
            "活动建议：通过观察、实验、练习、讨论等方式深化对「秦汉统一与中央集权制度」的理解"
          ]
        },
        {
          "id": "hist-h-qin-han-empire",
          "name": "秦汉帝国",
          "grade": 10,
          "prerequisites": [
            "hist-h-feudal-system"
          ],
          "extends": [],
          "parallel": [],
          "courses": [],
          "status": "gap",
          "curriculum_points": [
            "高中10年级学段目标：理解并掌握「秦汉帝国」的基本概念与方法",
            "学业要求：能在真实情境中识别、运用「秦汉帝国」解决问题",
            "活动建议：通过观察、实验、练习、讨论等方式深化对「秦汉帝国」的理解"
          ]
        },
        {
          "id": "hist-h-imperial-system",
          "name": "隋唐至明清政治制度演变",
          "grade": 10,
          "prerequisites": [
            "hist-h-qin-han-empire"
          ],
          "extends": [],
          "parallel": [],
          "courses": [],
          "status": "gap",
          "curriculum_points": [
            "高中10年级学段目标：理解并掌握「隋唐至明清政治制度演变」的基本概念与方法",
            "学业要求：能在真实情境中识别、运用「隋唐至明清政治制度演变」解决问题",
            "活动建议：通过观察、实验、练习、讨论等方式深化对「隋唐至明清政治制度演变」的理解"
          ]
        },
        {
          "id": "hist-h-wei-jin-tang",
          "name": "三国两晋南北朝与隋唐",
          "grade": 10,
          "prerequisites": [
            "hist-h-imperial-system"
          ],
          "extends": [],
          "parallel": [],
          "courses": [],
          "status": "gap",
          "curriculum_points": [
            "高中10年级学段目标：理解并掌握「三国两晋南北朝与隋唐」的基本概念与方法",
            "学业要求：能在真实情境中识别、运用「三国两晋南北朝与隋唐」解决问题",
            "活动建议：通过观察、实验、练习、讨论等方式深化对「三国两晋南北朝与隋唐」的理解"
          ]
        },
        {
          "id": "hist-h-song-yuan-ming-qing-h",
          "name": "宋元明清",
          "grade": 10,
          "prerequisites": [
            "hist-h-wei-jin-tang"
          ],
          "extends": [],
          "parallel": [],
          "courses": [],
          "status": "gap",
          "curriculum_points": [
            "高中10年级学段目标：理解并掌握「宋元明清」的基本概念与方法",
            "学业要求：能在真实情境中识别、运用「宋元明清」解决问题",
            "活动建议：通过观察、实验、练习、讨论等方式深化对「宋元明清」的理解"
          ]
        },
        {
          "id": "hist-h-ancient-economy",
          "name": "古代经济（农业/手工业/商业）",
          "grade": 10,
          "prerequisites": [
            "hist-h-song-yuan-ming-qing-h"
          ],
          "extends": [],
          "parallel": [],
          "courses": [],
          "status": "gap",
          "name_en": "Agriculture / Industry",
          "curriculum_points": [
            "高中10年级学段目标：理解并掌握「古代经济（农业/手工业/商业）」的基本概念与方法",
            "学业要求：能在真实情境中识别、运用「古代经济（农业/手工业/商业）」解决问题",
            "活动建议：通过观察、实验、练习、讨论等方式深化对「古代经济（农业/手工业/商业）」的理解"
          ]
        },
        {
          "id": "hist-h-ancient-culture",
          "name": "中国古代思想文化",
          "grade": 10,
          "prerequisites": [
            "hist-h-song-yuan-ming-qing-h"
          ],
          "extends": [],
          "parallel": [],
          "courses": [],
          "status": "gap",
          "curriculum_points": [
            "高中10年级学段目标：理解并掌握「中国古代思想文化」的基本概念与方法",
            "学业要求：能在真实情境中识别、运用「中国古代思想文化」解决问题",
            "活动建议：通过观察、实验、练习、讨论等方式深化对「中国古代思想文化」的理解"
          ]
        },
        {
          "id": "hist-h-ancient-thought",
          "name": "古代思想文化（儒/道/法/佛）",
          "grade": 10,
          "prerequisites": [
            "hist-h-ancient-culture"
          ],
          "extends": [],
          "parallel": [],
          "courses": [],
          "status": "gap",
          "curriculum_points": [
            "高中10年级学段目标：理解并掌握「古代思想文化（儒/道/法/佛）」的基本概念与方法",
            "学业要求：能在真实情境中识别、运用「古代思想文化（儒/道/法/佛）」解决问题",
            "活动建议：通过观察、实验、练习、讨论等方式深化对「古代思想文化（儒/道/法/佛）」的理解"
          ]
        }
      ],
      "curriculum_goal": "《普通高中历史课程标准（2017年版2020年修订）》规定的「中国古代史」领域内容要求：落实 history 学科核心素养，在高中阶段系统化掌握该领域关键概念与能力。"
    },
    {
      "id": "modern-china-h",
      "name": "中国近现代史",
      "color": "#f59e0b",
      "nodes": [
        {
          "id": "hist-h-opium-war-h",
          "name": "鸦片战争与近代中国",
          "grade": 10,
          "prerequisites": [
            "hist-h-ancient-thought"
          ],
          "extends": [],
          "parallel": [],
          "courses": [],
          "status": "gap",
          "curriculum_points": [
            "高中10年级学段目标：理解并掌握「鸦片战争与近代中国」的基本概念与方法",
            "学业要求：能在真实情境中识别、运用「鸦片战争与近代中国」解决问题",
            "活动建议：通过观察、实验、练习、讨论等方式深化对「鸦片战争与近代中国」的理解"
          ]
        },
        {
          "id": "hist-h-semi-colonial",
          "name": "半殖民地半封建社会的形成",
          "grade": 10,
          "prerequisites": [
            "hist-h-opium-war-h"
          ],
          "extends": [],
          "parallel": [],
          "courses": [],
          "status": "gap",
          "curriculum_points": [
            "高中10年级学段目标：理解并掌握「半殖民地半封建社会的形成」的基本概念与方法",
            "学业要求：能在真实情境中识别、运用「半殖民地半封建社会的形成」解决问题",
            "活动建议：通过观察、实验、练习、讨论等方式深化对「半殖民地半封建社会的形成」的理解"
          ]
        },
        {
          "id": "hist-h-reform-revolution-h",
          "name": "戊戌变法与辛亥革命",
          "grade": 10,
          "prerequisites": [
            "hist-h-semi-colonial"
          ],
          "extends": [],
          "parallel": [],
          "courses": [],
          "status": "gap",
          "curriculum_points": [
            "高中10年级学段目标：理解并掌握「戊戌变法与辛亥革命」的基本概念与方法",
            "学业要求：能在真实情境中识别、运用「戊戌变法与辛亥革命」解决问题",
            "活动建议：通过观察、实验、练习、讨论等方式深化对「戊戌变法与辛亥革命」的理解"
          ]
        },
        {
          "id": "hist-h-xinhai-modern",
          "name": "辛亥革命与民国建立",
          "grade": 10,
          "prerequisites": [
            "hist-h-reform-revolution-h"
          ],
          "extends": [],
          "parallel": [],
          "courses": [],
          "status": "gap",
          "curriculum_points": [
            "高中10年级学段目标：理解并掌握「辛亥革命与民国建立」的基本概念与方法",
            "学业要求：能在真实情境中识别、运用「辛亥革命与民国建立」解决问题",
            "活动建议：通过观察、实验、练习、讨论等方式深化对「辛亥革命与民国建立」的理解"
          ]
        },
        {
          "id": "hist-h-new-democracy",
          "name": "新民主主义革命",
          "grade": 10,
          "prerequisites": [
            "hist-h-xinhai-modern"
          ],
          "extends": [],
          "parallel": [],
          "courses": [],
          "status": "gap",
          "curriculum_points": [
            "高中10年级学段目标：理解并掌握「新民主主义革命」的基本概念与方法",
            "学业要求：能在真实情境中识别、运用「新民主主义革命」解决问题",
            "活动建议：通过观察、实验、练习、讨论等方式深化对「新民主主义革命」的理解"
          ]
        },
        {
          "id": "hist-h-prc-establishment",
          "name": "中华人民共和国成立",
          "grade": 11,
          "prerequisites": [
            "hist-h-new-democracy"
          ],
          "extends": [],
          "parallel": [],
          "courses": [],
          "status": "gap",
          "curriculum_points": [
            "高中11年级学段目标：理解并掌握「中华人民共和国成立」的基本概念与方法",
            "学业要求：能在真实情境中识别、运用「中华人民共和国成立」解决问题",
            "活动建议：通过观察、实验、练习、讨论等方式深化对「中华人民共和国成立」的理解"
          ]
        },
        {
          "id": "hist-h-reform-opening",
          "name": "改革开放",
          "grade": 11,
          "prerequisites": [
            "hist-h-prc-establishment"
          ],
          "extends": [],
          "parallel": [],
          "courses": [],
          "status": "gap",
          "curriculum_points": [
            "高中11年级学段目标：理解并掌握「改革开放」的基本概念与方法",
            "学业要求：能在真实情境中识别、运用「改革开放」解决问题",
            "活动建议：通过观察、实验、练习、讨论等方式深化对「改革开放」的理解"
          ]
        }
      ],
      "curriculum_goal": "《普通高中历史课程标准（2017年版2020年修订）》规定的「中国近现代史」领域内容要求：落实 history 学科核心素养，在高中阶段系统化掌握该领域关键概念与能力。"
    },
    {
      "id": "world-ancient-h",
      "name": "世界古代中世纪史",
      "color": "#10b981",
      "nodes": [
        {
          "id": "hist-h-ancient-civ-h",
          "name": "古代亚非欧文明",
          "grade": 11,
          "prerequisites": [],
          "extends": [],
          "parallel": [],
          "courses": [],
          "status": "gap",
          "curriculum_points": [
            "高中11年级学段目标：理解并掌握「古代亚非欧文明」的基本概念与方法",
            "学业要求：能在真实情境中识别、运用「古代亚非欧文明」解决问题",
            "活动建议：通过观察、实验、练习、讨论等方式深化对「古代亚非欧文明」的理解"
          ]
        },
        {
          "id": "hist-h-medieval-h",
          "name": "中古时期（欧洲/亚洲/非洲美洲）",
          "grade": 11,
          "prerequisites": [
            "hist-h-ancient-civ-h"
          ],
          "extends": [],
          "parallel": [],
          "courses": [],
          "status": "gap",
          "curriculum_points": [
            "高中11年级学段目标：理解并掌握「中古时期（欧洲/亚洲/非洲美洲）」的基本概念与方法",
            "学业要求：能在真实情境中识别、运用「中古时期（欧洲/亚洲/非洲美洲）」解决问题",
            "活动建议：通过观察、实验、练习、讨论等方式深化对「中古时期（欧洲/亚洲/非洲美洲）」的理解"
          ]
        }
      ],
      "curriculum_goal": "《普通高中历史课程标准（2017年版2020年修订）》规定的「世界古代中世纪史」领域内容要求：落实 history 学科核心素养，在高中阶段系统化掌握该领域关键概念与能力。"
    },
    {
      "id": "world-modern-h",
      "name": "世界近现代史",
      "color": "#3b82f6",
      "nodes": [
        {
          "id": "hist-h-age-of-exploration",
          "name": "新航路开辟与殖民扩张",
          "grade": 11,
          "prerequisites": [
            "hist-h-medieval-h"
          ],
          "extends": [],
          "parallel": [],
          "courses": [],
          "status": "gap",
          "curriculum_points": [
            "高中11年级学段目标：理解并掌握「新航路开辟与殖民扩张」的基本概念与方法",
            "学业要求：能在真实情境中识别、运用「新航路开辟与殖民扩张」解决问题",
            "活动建议：通过观察、实验、练习、讨论等方式深化对「新航路开辟与殖民扩张」的理解"
          ]
        },
        {
          "id": "hist-h-enlightenment",
          "name": "文艺复兴、宗教改革与启蒙运动",
          "grade": 11,
          "prerequisites": [
            "hist-h-age-of-exploration"
          ],
          "extends": [],
          "parallel": [],
          "courses": [],
          "status": "gap",
          "name_en": "Renaissance",
          "curriculum_points": [
            "高中11年级学段目标：理解并掌握「文艺复兴、宗教改革与启蒙运动」的基本概念与方法",
            "学业要求：能在真实情境中识别、运用「文艺复兴、宗教改革与启蒙运动」解决问题",
            "活动建议：通过观察、实验、练习、讨论等方式深化对「文艺复兴、宗教改革与启蒙运动」的理解"
          ]
        },
        {
          "id": "hist-h-industrial-rev-h",
          "name": "工业革命",
          "grade": 11,
          "prerequisites": [
            "hist-h-enlightenment"
          ],
          "extends": [],
          "parallel": [],
          "courses": [],
          "status": "gap",
          "name_en": "Industrial Revolution",
          "curriculum_points": [
            "高中11年级学段目标：理解并掌握「工业革命」的基本概念与方法",
            "学业要求：能在真实情境中识别、运用「工业革命」解决问题",
            "活动建议：通过观察、实验、练习、讨论等方式深化对「工业革命」的理解"
          ]
        },
        {
          "id": "hist-h-marxism-russian",
          "name": "马克思主义与俄国革命",
          "grade": 11,
          "prerequisites": [
            "hist-h-industrial-rev-h"
          ],
          "extends": [],
          "parallel": [],
          "courses": [],
          "status": "gap",
          "curriculum_points": [
            "高中11年级学段目标：理解并掌握「马克思主义与俄国革命」的基本概念与方法",
            "学业要求：能在真实情境中识别、运用「马克思主义与俄国革命」解决问题",
            "活动建议：通过观察、实验、练习、讨论等方式深化对「马克思主义与俄国革命」的理解"
          ]
        },
        {
          "id": "hist-h-two-world-wars",
          "name": "两次世界大战",
          "grade": 12,
          "prerequisites": [
            "hist-h-marxism-russian"
          ],
          "extends": [],
          "parallel": [],
          "courses": [],
          "status": "gap",
          "name_en": "Two World Wars",
          "curriculum_points": [
            "高中12年级学段目标：理解并掌握「两次世界大战」的基本概念与方法",
            "学业要求：能在真实情境中识别、运用「两次世界大战」解决问题",
            "活动建议：通过观察、实验、练习、讨论等方式深化对「两次世界大战」的理解"
          ]
        },
        {
          "id": "hist-h-cold-war-h",
          "name": "冷战格局",
          "grade": 12,
          "prerequisites": [
            "hist-h-two-world-wars"
          ],
          "extends": [],
          "parallel": [],
          "courses": [],
          "status": "gap",
          "name_en": "Cold War",
          "curriculum_points": [
            "高中12年级学段目标：理解并掌握「冷战格局」的基本概念与方法",
            "学业要求：能在真实情境中识别、运用「冷战格局」解决问题",
            "活动建议：通过观察、实验、练习、讨论等方式深化对「冷战格局」的理解"
          ]
        },
        {
          "id": "hist-h-globalization-h",
          "name": "全球化与多极化",
          "grade": 12,
          "prerequisites": [
            "hist-h-cold-war-h"
          ],
          "extends": [],
          "parallel": [],
          "courses": [],
          "status": "gap",
          "name_en": "Sphere",
          "curriculum_points": [
            "高中12年级学段目标：理解并掌握「全球化与多极化」的基本概念与方法",
            "学业要求：能在真实情境中识别、运用「全球化与多极化」解决问题",
            "活动建议：通过观察、实验、练习、讨论等方式深化对「全球化与多极化」的理解"
          ]
        }
      ],
      "curriculum_goal": "《普通高中历史课程标准（2017年版2020年修订）》规定的「世界近现代史」领域内容要求：落实 history 学科核心素养，在高中阶段系统化掌握该领域关键概念与能力。"
    },
    {
      "id": "thematic-history",
      "name": "专题史（选择性必修）",
      "color": "#a855f7",
      "nodes": [
        {
          "id": "hist-h-political-system-evolution",
          "name": "中外政治制度演变",
          "grade": 11,
          "prerequisites": [
            "hist-h-song-yuan-ming-qing-h"
          ],
          "extends": [],
          "parallel": [],
          "courses": [],
          "status": "gap",
          "curriculum_points": [
            "高中11年级学段目标：理解并掌握「中外政治制度演变」的基本概念与方法",
            "学业要求：能在真实情境中识别、运用「中外政治制度演变」解决问题",
            "活动建议：通过观察、实验、练习、讨论等方式深化对「中外政治制度演变」的理解"
          ]
        },
        {
          "id": "hist-h-economic-history",
          "name": "经济史与社会生活",
          "grade": 11,
          "prerequisites": [
            "hist-h-industrial-rev-h"
          ],
          "extends": [],
          "parallel": [],
          "courses": [],
          "status": "gap",
          "curriculum_points": [
            "高中11年级学段目标：理解并掌握「经济史与社会生活」的基本概念与方法",
            "学业要求：能在真实情境中识别、运用「经济史与社会生活」解决问题",
            "活动建议：通过观察、实验、练习、讨论等方式深化对「经济史与社会生活」的理解"
          ]
        },
        {
          "id": "hist-h-cultural-thought-history",
          "name": "文化史与思想史",
          "grade": 12,
          "prerequisites": [
            "hist-h-ancient-culture",
            "hist-h-enlightenment"
          ],
          "extends": [],
          "parallel": [],
          "courses": [],
          "status": "gap",
          "curriculum_points": [
            "高中12年级学段目标：理解并掌握「文化史与思想史」的基本概念与方法",
            "学业要求：能在真实情境中识别、运用「文化史与思想史」解决问题",
            "活动建议：通过观察、实验、练习、讨论等方式深化对「文化史与思想史」的理解"
          ]
        },
        {
          "id": "hist-h-science-technology-h",
          "name": "科技史",
          "grade": 12,
          "prerequisites": [
            "hist-h-industrial-rev-h"
          ],
          "extends": [],
          "parallel": [],
          "courses": [],
          "status": "gap",
          "curriculum_points": [
            "高中12年级学段目标：理解并掌握「科技史」的基本概念与方法",
            "学业要求：能在真实情境中识别、运用「科技史」解决问题",
            "活动建议：通过观察、实验、练习、讨论等方式深化对「科技史」的理解"
          ]
        },
        {
          "id": "hist-h-ideological-liberation",
          "name": "思想解放潮流",
          "grade": 12,
          "prerequisites": [
            "hist-h-enlightenment"
          ],
          "extends": [],
          "parallel": [],
          "courses": [],
          "status": "gap",
          "curriculum_points": [
            "高中12年级学段目标：理解并掌握「思想解放潮流」的基本概念与方法",
            "学业要求：能在真实情境中识别、运用「思想解放潮流」解决问题",
            "活动建议：通过观察、实验、练习、讨论等方式深化对「思想解放潮流」的理解"
          ]
        },
        {
          "id": "hist-h-reform-comparison",
          "name": "中外改革比较",
          "grade": 12,
          "prerequisites": [
            "hist-h-reform-opening"
          ],
          "extends": [],
          "parallel": [],
          "courses": [],
          "status": "gap",
          "curriculum_points": [
            "高中12年级学段目标：理解并掌握「中外改革比较」的基本概念与方法",
            "学业要求：能在真实情境中识别、运用「中外改革比较」解决问题",
            "活动建议：通过观察、实验、练习、讨论等方式深化对「中外改革比较」的理解"
          ]
        }
      ],
      "curriculum_goal": "《普通高中历史课程标准（2017年版2020年修订）》规定的「专题史（选择性必修）」领域内容要求：落实 history 学科核心素养，在高中阶段系统化掌握该领域关键概念与能力。"
    }
  ],
  "metadata": {
    "curriculum": {
      "standard": "普通高中历史课程标准（2017年版2020年修订）",
      "standard_en": "Senior High History Curriculum Standard (2017, rev. 2020)",
      "stage_key": "high",
      "stage_zh": "高中",
      "source": "中华人民共和国教育部",
      "issued": "2020-05",
      "grade_range": [
        10,
        12
      ],
      "core_concepts": [
        "唯物史观",
        "时空观念",
        "史料实证",
        "历史解释",
        "家国情怀"
      ],
      "stage_goals": [
        "必修（4 学分）：中外历史纲要（上/下）",
        "选择性必修（6 学分）：国家制度与社会治理/经济与社会生活/文化交流与传播",
        "选修：史学入门/史料研读"
      ],
      "assessment": "学业质量分 4 级；高考对标 3 级；强调历史解释从'事实层'→'评价层'→'反思层'递进。",
      "references": [
        "学科核心素养 (3)",
        "课程内容 (4)",
        "学业质量 (5)"
      ],
      "node_count": 33
    },
    "updated_at": "2026-04-19"
  }
}
