{
  "subject": "history",
  "domain": "modern-china",
  "version": "1.0",
  "curriculum": "人教版（部编版）",
  "nodes": [
    {
      "id": "hist-m-opium-war-era",
      "name": "列强侵华与民族危机",
      "name_en": "Foreign Aggression and National Crisis",
      "grade": "8",
      "semester": "上",
      "unit": "第1-2单元",
      "definition": "从鸦片战争到八国联军侵华，中国逐步沦为半殖民地半封建社会",
      "key_concepts": [
        "鸦片战争（1840）与《南京条约》",
        "第二次鸦片战争",
        "甲午中日战争与《马关条约》",
        "八国联军侵华与《辛丑条约》",
        "不平等条约体系"
      ],
      "prerequisites": [],
      "leads_to": [
        "hist-m-reform-revolution",
        "hist-m-new-democratic-revolution"
      ],
      "real_world": [
        "圆明园遗址——列强侵略的见证",
        "香港回归——收回鸦片战争失去的领土",
        "「落后就要挨打」——历史教训"
      ],
      "memory_anchors": [
        "三大条约递进：南京条约（割地赔款开端）→马关条约（割台湾、允设厂）→辛丑条约（最严重）",
        "半殖民地半封建：主权不完整但不是完全丧失，有封建残余但不是纯粹封建"
      ],
      "bloom_verbs": {
        "remember": "列出三大不平等条约的主要内容",
        "understand": "解释半殖民地半封建社会的含义",
        "apply": "用时间轴梳理列强侵华的过程",
        "analyze": "分析中国战败的深层原因",
        "evaluate": "评价不平等条约对中国的影响",
        "create": "比较三次侵华战争的异同"
      },
      "curriculum_standards": {
        "source": "《义务教育历史课程标准（2022年版）》· 中国近代史 → 列强侵略与民族危机",
        "content_requirements": [
          "① 通过了解林则徐虎门销烟、英法联军火烧圆明园、俄国割占中国北方大片领土等两次鸦片战争期间的主要史实，以及《南京条约》等不平等条约的签订，初步认识鸦片战争对中国近代社会的影响。",
          "② 了解太平天国运动的兴衰；了解洋务运动的主要内容和局限性；了解19世纪中后期的边疆危机和中法战争。",
          "③ 知道甲午中日战争的主要战役和《马关条约》的主要内容；初步认识《马关条约》与中国民族危机加剧的关系。"
        ]
      }
    },
    {
      "id": "hist-m-reform-revolution",
      "name": "近代化探索",
      "name_en": "Modernization Exploration",
      "grade": "8",
      "semester": "上",
      "unit": "第3-4单元",
      "definition": "面对民族危机，中国各阶层进行了洋务运动、戊戌变法、辛亥革命、新文化运动等一系列近代化探索",
      "key_concepts": [
        "洋务运动：「师夷长技」——器物层面",
        "戊戌变法：「变法图强」——制度层面",
        "辛亥革命：推翻帝制建立民国",
        "新文化运动：「民主与科学」——思想层面",
        "探索的层次递进：器物→制度→思想"
      ],
      "prerequisites": [
        "hist-m-opium-war-era"
      ],
      "leads_to": [
        "hist-m-new-democratic-revolution"
      ],
      "real_world": [
        "辛亥革命结束了两千多年的封建帝制",
        "新文化运动提倡白话文——影响至今",
        "「中学为体，西学为用」的历史局限"
      ],
      "memory_anchors": [
        "近代化探索层层深入：洋务（学技术）→维新（改制度）→革命（换政体）→新文化（变思想）",
        "洋务运动口号：自强（军事）、求富（民用）"
      ],
      "bloom_verbs": {
        "remember": "说出四次近代化探索的名称和主要内容",
        "understand": "解释近代化探索为什么层层深入",
        "apply": "用表格对比四次探索的异同",
        "analyze": "分析各次探索失败的原因",
        "evaluate": "评价辛亥革命的历史意义和局限",
        "create": "论述中国近代化道路的特点"
      },
      "curriculum_standards": {
        "source": "《义务教育历史课程标准（2022年版）》· 中国近代史 → 救亡图存探索",
        "content_requirements": [
          "① 了解戊戌变法（康有为/梁启超/谭嗣同）的内容、失败原因和历史意义；理解改良道路在中国行不通的原因。",
          "② 了解孙中山等民主革命先驱者早年的革命活动和武昌起义及中华民国成立的历史意义及局限性。",
          "③ 知道民国初期北洋军阀的统治；了解新文化运动的基本内容和代表人物（陈独秀/李大钊/胡适/鲁迅）。"
        ]
      }
    },
    {
      "id": "hist-m-new-democratic-revolution",
      "name": "新民主主义革命",
      "name_en": "New Democratic Revolution",
      "grade": "8",
      "semester": "下",
      "unit": "第1-5单元",
      "definition": "从五四运动到新中国成立（1919-1949），在中国共产党领导下，经过北伐、土地革命、抗日战争、解放战争，最终建立新中国",
      "key_concepts": [
        "五四运动（1919）——新民主主义革命的开端",
        "中国共产党成立（1921）",
        "长征与遵义会议",
        "抗日战争（1931-1945）",
        "解放战争与新中国成立（1949）"
      ],
      "prerequisites": [
        "hist-m-opium-war-era",
        "hist-m-reform-revolution"
      ],
      "leads_to": [
        "hist-m-modern-china-development"
      ],
      "real_world": [
        "五四精神——爱国、进步、民主、科学",
        "长征精神——不怕困难、坚定信念",
        "抗日战争的全民族抗战"
      ],
      "memory_anchors": [
        "重要时间线：1919五四→1921建党→1927南昌起义→1934长征→1937全面抗战→1949建国",
        "「星星之火，可以燎原」——农村包围城市的道路"
      ],
      "bloom_verbs": {
        "remember": "说出新民主主义革命的主要事件和时间",
        "understand": "解释五四运动的历史意义",
        "apply": "用时间轴梳理革命进程",
        "analyze": "分析中国革命道路选择的原因",
        "evaluate": "评价遵义会议的历史意义",
        "create": "论述新民主主义革命的基本经验"
      },
      "curriculum_standards": {
        "source": "《义务教育历史课程标准（2022年版）》· 中国近代史 → 新民主主义革命兴起",
        "content_requirements": [
          "① 通过了解五四运动的基本史事，理解五四精神是中国新民主主义革命的开端。",
          "② 通过了解陈独秀、李大钊传播马克思主义和中国共产党第一次全国代表大会的召开等史事，认识中国共产党成立与新民主主义革命兴起的关联。",
          "③ 了解北伐战争和国共合作破裂后的武装斗争；了解农村革命根据地（井冈山）的建立和土地革命。"
        ]
      }
    },
    {
      "id": "hist-m-modern-china-development",
      "name": "社会主义建设与改革开放",
      "name_en": "Socialist Construction and Reform",
      "grade": "8",
      "semester": "下",
      "unit": "第6单元",
      "definition": "新中国成立后，经历社会主义改造、探索建设、改革开放等阶段，走出了中国特色社会主义道路",
      "key_concepts": [
        "社会主义改造（1953-1956）",
        "社会主义建设的探索与曲折",
        "改革开放（1978至今）",
        "经济特区与对外开放",
        "中国特色社会主义道路"
      ],
      "prerequisites": [
        "hist-m-new-democratic-revolution"
      ],
      "leads_to": [],
      "real_world": [
        "深圳从小渔村到大都市——经济特区的成功",
        "改革开放四十多年的巨大成就",
        "「一带一路」——新时代的对外开放"
      ],
      "memory_anchors": [
        "改革开放关键节点：1978十一届三中全会→经济特区→加入WTO→全面深化改革",
        "经济特区：深圳、珠海、汕头、厦门——最早的四个窗口"
      ],
      "bloom_verbs": {
        "remember": "说出改革开放的主要历程",
        "understand": "解释社会主义改造的必要性",
        "apply": "用数据说明改革开放的成就",
        "analyze": "分析中国选择改革开放的历史背景",
        "evaluate": "评价改革开放的历史意义",
        "create": "论述中国发展道路的特色和经验"
      },
      "curriculum_standards": {
        "source": "《义务教育历史课程标准（2022年版）》· 中国现代史 → 社会主义建设与改革开放",
        "content_requirements": [
          "① 了解中华人民共和国成立（1949年10月1日）的历史意义；理解中国人民从此站起来了。",
          "② 了解社会主义制度在中国的建立（三大改造完成1956年）；了解探索建设社会主义道路中的成就与曲折（大跃进/人民公社化运动/文化大革命的经验教训）。",
          "③ 理解十一届三中全会（1978年）和改革开放的历史意义；了解中国特色社会主义道路的探索与发展。"
        ]
      }
    }
  ],
  "edges": [
    {
      "from": "hist-m-opium-war-era",
      "to": "hist-m-reform-revolution",
      "type": "prerequisite",
      "note": "列强侵略激发近代化探索"
    },
    {
      "from": "hist-m-opium-war-era",
      "to": "hist-m-new-democratic-revolution",
      "type": "prerequisite",
      "note": "民族危机是革命的根源"
    },
    {
      "from": "hist-m-reform-revolution",
      "to": "hist-m-new-democratic-revolution",
      "type": "prerequisite",
      "note": "旧民主主义革命为新民主主义革命奠基"
    },
    {
      "from": "hist-m-new-democratic-revolution",
      "to": "hist-m-modern-china-development",
      "type": "prerequisite",
      "note": "革命胜利后进入建设时期"
    }
  ]
}
