{
  "subject": "math",
  "domain": "high-school",
  "version": "1.0",
  "curriculum": "人教A版（2019新课标）",
  "nodes": [
    {
      "id": "sets-logic",
      "name": "集合与常用逻辑用语",
      "name_en": "Sets and Logic",
      "grade": "10",
      "semester": "上",
      "unit": "必修一 第1章",
      "definition": "集合是具有某种确定性质的对象的全体，掌握集合的运算和常用逻辑用语",
      "key_concepts": [
        "集合的三种表示法：列举法、描述法、图示法",
        "子集、真子集、空集",
        "交集A∩B、并集A∪B、补集∁ᵤA",
        "充分条件、必要条件、充要条件",
        "全称量词∀和存在量词∃",
        "命题的否定"
      ],
      "prerequisites": [],
      "leads_to": ["functions-advanced", "inequalities-advanced"],
      "real_world": ["分类整理就是建立集合", "法律条文中的'充分条件'和'必要条件'"],
      "memory_anchors": ["集合就是'圈一堆'——把符合条件的东西圈在一起", "交集是'都要有'，并集是'全都算'，补集是'没选上的'", "充分条件：有它就够（充分），必要条件：没它不行（必要）"],
      "bloom_verbs": {
        "remember": "写出集合运算的定义",
        "understand": "用韦恩图解释交集和并集",
        "apply": "求{1,2,3}∩{2,3,4}",
        "analyze": "判断'x>2'是'x>1'的什么条件",
        "evaluate": "判断命题的逆否命题是否成立",
        "create": "构造一个满足特定交并条件的集合"
      }
    },
    {
      "id": "functions-advanced",
      "name": "函数（高中）",
      "name_en": "Functions (Senior High)",
      "grade": "10",
      "semester": "上",
      "unit": "必修一 第2-4章",
      "definition": "从映射角度重新认识函数，掌握指数函数、对数函数、幂函数的图像与性质",
      "key_concepts": [
        "函数的定义域、值域、对应法则",
        "函数的单调性、奇偶性、周期性",
        "指数函数y=aˣ(a>0,a≠1)的图像与性质",
        "对数函数y=logₐx(a>0,a≠1)的图像与性质",
        "指数与对数的互逆关系",
        "幂函数y=xⁿ的图像",
        "函数零点与方程的根"
      ],
      "prerequisites": ["sets-logic", "quadratic-function"],
      "leads_to": ["trigonometric-functions", "derivatives"],
      "real_world": ["人口增长是指数函数", "地震烈度用对数表示", "放射性衰变是指数衰减"],
      "memory_anchors": ["指数函数'指数爆炸'——底数>1越长越快，0<底数<1越来越慢", "对数是指数的'反操作'——2³=8, log₂8=3", "奇函数关于原点对称（奇=鸡=J形），偶函数关于y轴对称（偶=U形）"],
      "bloom_verbs": {
        "remember": "画出指数函数和对数函数的图像",
        "understand": "解释指数函数和对数函数互逆的含义",
        "apply": "求函数f(x)=log₂(x-1)的定义域",
        "analyze": "比较两个指数式的大小",
        "evaluate": "利用函数零点定理判断方程根的个数",
        "create": "建立指数函数模型解决人口增长问题"
      }
    },
    {
      "id": "trigonometric-functions",
      "name": "三角函数",
      "name_en": "Trigonometric Functions",
      "grade": "10",
      "semester": "下",
      "unit": "必修一 第5章/必修二 第6章",
      "definition": "用单位圆定义三角函数，掌握正弦、余弦、正切函数的图像与性质及三角恒等变换",
      "key_concepts": [
        "任意角与弧度制",
        "单位圆定义三角函数",
        "y=sin x, y=cos x, y=tan x 的图像和性质",
        "y=Asin(ωx+φ) 的图像变换",
        "同角三角函数基本关系：sin²x+cos²x=1",
        "两角和与差公式",
        "二倍角公式",
        "辅助角公式"
      ],
      "prerequisites": ["functions-advanced"],
      "leads_to": ["trigonometry-solution", "derivatives"],
      "real_world": ["声波是正弦曲线", "摩天轮的高度变化", "交流电的电压波形"],
      "memory_anchors": ["弧度就是用半径量弧长：π=180°", "sin的图像像'波浪'，cos就是sin左移π/2", "两角和差公式口诀：正余余正/余余正正符号看加减"],
      "bloom_verbs": {
        "remember": "写出两角和差的正弦余弦公式",
        "understand": "解释弧度制的含义",
        "apply": "求sin75°的值",
        "analyze": "由y=Asin(ωx+φ)的图像确定A、ω、φ",
        "evaluate": "验证一个三角恒等式",
        "create": "用三角函数建模周期性变化问题"
      }
    },
    {
      "id": "trigonometry-solution",
      "name": "解三角形",
      "name_en": "Solving Triangles",
      "grade": "11",
      "semester": "上",
      "unit": "必修二 第7章",
      "definition": "掌握正弦定理和余弦定理，能解任意三角形",
      "key_concepts": [
        "正弦定理：a/sinA=b/sinB=c/sinC=2R",
        "余弦定理：a²=b²+c²-2bc·cosA",
        "三角形面积公式：S=½ab·sinC",
        "解三角形的应用：测量、航海、测绘"
      ],
      "prerequisites": ["trigonometric-functions"],
      "leads_to": [],
      "real_world": ["测量河对岸建筑高度", "航海中两船距离", "测量山的高度"],
      "memory_anchors": ["正弦定理管'边角对应'，余弦定理管'三边和一角'", "余弦定理是勾股定理的推广——当C=90°时cosC=0就变成a²+b²=c²"],
      "bloom_verbs": {
        "remember": "写出正弦定理和余弦定理",
        "understand": "解释余弦定理与勾股定理的关系",
        "apply": "已知两边及夹角求第三边",
        "analyze": "判断用正弦定理还是余弦定理",
        "evaluate": "解三角形时判断解的个数",
        "create": "设计一个实地测量问题并用解三角形求解"
      }
    },
    {
      "id": "sequences",
      "name": "数列",
      "name_en": "Sequences and Series",
      "grade": "11",
      "semester": "上",
      "unit": "必修二 第8章",
      "definition": "掌握等差数列和等比数列的通项公式和求和公式",
      "key_concepts": [
        "数列的概念：按一定规律排列的一列数",
        "等差数列通项公式：aₙ=a₁+(n-1)d",
        "等差数列求和：Sₙ=n(a₁+aₙ)/2",
        "等比数列通项公式：aₙ=a₁·qⁿ⁻¹",
        "等比数列求和：Sₙ=a₁(1-qⁿ)/(1-q) (q≠1)",
        "数列与函数的关系"
      ],
      "prerequisites": ["functions-advanced"],
      "leads_to": ["derivatives"],
      "real_world": ["存款利息（等比）", "等距种树（等差）", "细胞分裂（等比）"],
      "memory_anchors": ["等差就是'等距离排队'——每次加同样的d", "等比就是'等倍数增长'——每次乘同样的q", "高斯求和故事：1+2+...+100=首末配对×对数=101×50=5050"],
      "bloom_verbs": {
        "remember": "写出等差和等比数列的通项公式和求和公式",
        "understand": "解释等差中项和等比中项的含义",
        "apply": "求等差数列前20项之和",
        "analyze": "判断一个数列是等差还是等比",
        "evaluate": "验证一个数列求和的结果",
        "create": "构造满足特定条件的数列"
      }
    },
    {
      "id": "inequalities-advanced",
      "name": "不等式（高中）",
      "name_en": "Inequalities (Senior High)",
      "grade": "10-11",
      "semester": "各学期",
      "unit": "必修一 第2章补充/选修",
      "definition": "掌握基本不等式和一元二次不等式的解法",
      "key_concepts": [
        "基本不等式：(a+b)/2 ≥ √(ab)（算术平均≥几何平均）",
        "基本不等式取等条件：a=b",
        "一元二次不等式ax²+bx+c>0的解法",
        "二次不等式与二次函数、二次方程的关系（三个二次联系）",
        "含参数不等式的讨论"
      ],
      "prerequisites": ["sets-logic", "quadratic-function"],
      "leads_to": ["linear-programming"],
      "real_world": ["最优化问题：用最少材料围最大面积", "成本最小化"],
      "memory_anchors": ["基本不等式口诀：'和定积最大，积定和最小'（均值不等式的两种用法）", "取等条件要牢记：一正二定三相等"],
      "bloom_verbs": {
        "remember": "写出基本不等式",
        "understand": "用几何法证明基本不等式",
        "apply": "求x+1/x(x>0)的最小值",
        "analyze": "解一元二次不等式并在数轴上表示",
        "evaluate": "检查最值问题中取等条件是否满足",
        "create": "用基本不等式解决最优化实际问题"
      }
    },
    {
      "id": "linear-programming",
      "name": "线性规划",
      "name_en": "Linear Programming",
      "grade": "11",
      "semester": "上",
      "unit": "选择性必修一",
      "definition": "在一组线性约束条件下求线性目标函数的最优值",
      "key_concepts": [
        "二元一次不等式表示平面区域",
        "约束条件确定可行域",
        "目标函数的几何含义",
        "最优解在可行域的顶点取得"
      ],
      "prerequisites": ["inequalities-advanced"],
      "leads_to": [],
      "real_world": ["工厂排产计划", "饮食营养搭配最低成本", "运输方案优化"],
      "memory_anchors": ["画区域→找顶点→代入比大小", "可行域就是'允许活动的范围'"],
      "bloom_verbs": {
        "remember": "说出线性规划的基本步骤",
        "understand": "解释为什么最优解在顶点",
        "apply": "画出可行域并求目标函数最大值",
        "analyze": "分析约束条件改变对最优解的影响",
        "evaluate": "验证最优解是否满足所有约束",
        "create": "建立生产排程的线性规划模型"
      }
    },
    {
      "id": "solid-geometry",
      "name": "立体几何",
      "name_en": "Solid Geometry",
      "grade": "10-11",
      "semester": "各学期",
      "unit": "必修二 第9章/选择性必修一",
      "definition": "研究空间中点、线、面的位置关系和空间几何体的度量",
      "key_concepts": [
        "空间中线线、线面、面面的位置关系",
        "平行关系的判定与性质",
        "垂直关系的判定与性质（线面垂直→面面垂直）",
        "空间几何体（棱柱、棱锥、圆柱、圆锥、球）",
        "三视图和直观图",
        "表面积和体积公式",
        "空间向量法（选修）"
      ],
      "prerequisites": ["geometry-congruent-triangles", "pythagorean-theorem"],
      "leads_to": ["vectors"],
      "real_world": ["建筑结构中的垂直和平行", "房间墙面与地面的关系", "球体表面积与足球"],
      "memory_anchors": ["线面垂直是核心：线⊥面中所有直线", "面面垂直判定：一面过另一面的垂线→两面垂直", "球的体积V=4/3πR³——'三分之四派R立方'"],
      "bloom_verbs": {
        "remember": "写出线面垂直的判定定理",
        "understand": "解释线面平行的直观含义",
        "apply": "证明正方体中两条对角线垂直",
        "analyze": "判断空间两条直线的位置关系",
        "evaluate": "检验空间几何证明是否严密",
        "create": "构造一个满足特定位置关系的空间模型"
      }
    },
    {
      "id": "vectors",
      "name": "平面向量与空间向量",
      "name_en": "Vectors",
      "grade": "10-11",
      "semester": "必修二/选择性必修一",
      "unit": "必修二 第6章/选择性必修一",
      "definition": "既有大小又有方向的量叫向量，掌握向量的运算和应用",
      "key_concepts": [
        "向量的加减法（三角形法则、平行四边形法则）",
        "数乘向量",
        "向量的坐标表示",
        "数量积（点积）：a⃗·b⃗=|a⃗||b⃗|cosθ",
        "向量平行和垂直的条件",
        "空间向量的坐标运算",
        "用空间向量求角度和距离"
      ],
      "prerequisites": ["trigonometric-functions", "solid-geometry"],
      "leads_to": ["analytic-geometry"],
      "real_world": ["力的合成与分解", "位移是向量", "导航中的方向和距离"],
      "memory_anchors": ["向量=箭头，有方向有长度", "点积为0→垂直（cos90°=0）", "空间向量是立体几何的'万能钥匙'——建系算坐标"],
      "bloom_verbs": {
        "remember": "说出向量点积的计算公式",
        "understand": "用图形解释向量加法的三角形法则",
        "apply": "计算两个向量的点积和夹角",
        "analyze": "用向量判断两条直线的位置关系",
        "evaluate": "检验空间向量法求出的角度是否正确",
        "create": "建立空间坐标系用向量法解决立体几何问题"
      }
    },
    {
      "id": "analytic-geometry",
      "name": "解析几何（圆锥曲线）",
      "name_en": "Analytic Geometry (Conic Sections)",
      "grade": "11",
      "semester": "下",
      "unit": "选择性必修一 第3-4章",
      "definition": "用代数方法研究几何图形，掌握直线、圆、椭圆、双曲线、抛物线的方程",
      "key_concepts": [
        "直线方程的几种形式（点斜式、斜截式、两点式、一般式）",
        "两直线的平行和垂直条件",
        "圆的标准方程和一般方程",
        "椭圆：x²/a²+y²/b²=1",
        "双曲线：x²/a²-y²/b²=1",
        "抛物线：y²=2px",
        "焦点、准线、离心率",
        "直线与圆锥曲线的位置关系"
      ],
      "prerequisites": ["vectors", "functions-advanced"],
      "leads_to": [],
      "real_world": ["卫星轨道是椭圆", "抛物面天线", "双曲线导航定位"],
      "memory_anchors": ["椭圆像'压扁的圆'——到两焦点距离之和为常数", "双曲线像'两个喇叭'——到两焦点距离之差为常数", "抛物线像'U型槽'——到焦点和准线距离相等", "离心率e衡量'有多扁'：e→0接近圆，e→1很扁"],
      "bloom_verbs": {
        "remember": "写出椭圆、双曲线、抛物线的标准方程",
        "understand": "解释离心率的几何含义",
        "apply": "求经过两点的椭圆方程",
        "analyze": "判断直线与椭圆的交点个数",
        "evaluate": "检验弦长公式的推导过程",
        "create": "设计一道联立直线与椭圆求弦长的综合题"
      }
    },
    {
      "id": "derivatives",
      "name": "导数及其应用",
      "name_en": "Derivatives and Applications",
      "grade": "11-12",
      "semester": "选择性必修二/三",
      "unit": "选择性必修二 第5章/选择性必修三",
      "definition": "导数是函数在某一点的瞬时变化率，掌握求导法则和导数的应用",
      "key_concepts": [
        "导数的定义：f'(x)=lim[f(x+Δx)-f(x)]/Δx",
        "基本求导公式（幂函数、三角函数、指数对数）",
        "求导法则：和差、积、商、链式法则",
        "导数与函数单调性：f'>0单调递增",
        "导数与极值、最值",
        "导数的几何意义：切线斜率"
      ],
      "prerequisites": ["functions-advanced", "trigonometric-functions", "sequences"],
      "leads_to": [],
      "real_world": ["汽车瞬时速度", "利润最大化的产量", "物体运动的加速度"],
      "memory_anchors": ["导数就是'变化的速度'", "f'>0上坡（递增），f'<0下坡（递减），f'=0山顶或山谷（极值点）", "(xⁿ)'=nxⁿ⁻¹——'指数搬前面，指数减1'"],
      "bloom_verbs": {
        "remember": "写出常见函数的导数公式",
        "understand": "解释导数的几何意义",
        "apply": "求f(x)=x³-3x的极值",
        "analyze": "利用导数讨论含参函数的单调性",
        "evaluate": "判断导数为0的点一定是极值点吗",
        "create": "构造一个有两个极值点的三次函数"
      }
    },
    {
      "id": "statistics-probability-senior",
      "name": "统计与概率（高中）",
      "name_en": "Statistics and Probability (Senior High)",
      "grade": "10-11",
      "semester": "各学期",
      "unit": "必修二 第10章/选择性必修三",
      "definition": "掌握抽样方法、数据分析、排列组合、概率分布",
      "key_concepts": [
        "抽样方法：简单随机、系统、分层",
        "频率分布直方图和茎叶图",
        "回归分析和相关系数",
        "排列数A(n,m)和组合数C(n,m)",
        "二项式定理",
        "条件概率P(B|A)",
        "独立事件和互斥事件",
        "离散型随机变量的分布表、期望、方差",
        "二项分布和正态分布"
      ],
      "prerequisites": ["statistics-probability-junior", "functions-advanced"],
      "leads_to": [],
      "real_world": ["民意调查的抽样方法", "高考填志愿的概率分析", "保险精算", "质量控制"],
      "memory_anchors": ["排列讲'顺序'（先后有区别），组合不讲'顺序'（只管选不管排）", "C(n,m)口诀：上面从n倒着乘m个，下面m的阶乘", "期望就是'长期平均值'，方差就是'波动大小'"],
      "bloom_verbs": {
        "remember": "写出排列组合公式",
        "understand": "区分排列和组合的应用场景",
        "apply": "计算C(10,3)",
        "analyze": "分析一个事件的概率分布",
        "evaluate": "判断抽样方法是否合理",
        "create": "设计一个调查方案并分析数据"
      }
    },
    {
      "id": "complex-numbers",
      "name": "复数",
      "name_en": "Complex Numbers",
      "grade": "11",
      "semester": "下",
      "unit": "选择性必修二 第4章",
      "definition": "形如a+bi(a,b∈R,i²=-1)的数叫复数，掌握复数的运算",
      "key_concepts": [
        "虚数单位i：i²=-1",
        "复数的实部和虚部",
        "复数的四则运算",
        "复平面和几何意义",
        "共轭复数"
      ],
      "prerequisites": ["real-numbers", "vectors"],
      "leads_to": [],
      "real_world": ["交流电路分析", "信号处理中的傅里叶变换", "分形图形"],
      "memory_anchors": ["i是'想象出来的数'（imaginary）", "i的周期：i¹=i, i²=-1, i³=-i, i⁴=1，四个一循环", "复平面：实轴是'现实'，虚轴是'想象'"],
      "bloom_verbs": {
        "remember": "说出i的四次幂的循环",
        "understand": "解释复数的几何意义",
        "apply": "计算(1+i)(2-i)",
        "analyze": "在复平面上表示复数的运算",
        "evaluate": "判断两个复数相等的条件",
        "create": "用复数解决几何中的旋转问题"
      }
    },
    {
      "id": "parametric-polar",
      "name": "参数方程与极坐标",
      "name_en": "Parametric Equations and Polar Coordinates",
      "grade": "11-12",
      "semester": "选修",
      "unit": "选修4-4 坐标系与参数方程",
      "definition": "参数方程用一个参数（通常为t或θ）同时表示x和y；极坐标用极径ρ和极角θ描述点的位置",
      "key_concepts": [
        "参数方程的概念：x=f(t), y=g(t)",
        "直线和圆的参数方程",
        "椭圆的参数方程：x=acosθ, y=bsinθ",
        "参数方程与普通方程的互化（消参法）",
        "极坐标系：极点、极轴、极径ρ、极角θ",
        "极坐标与直角坐标的互化：x=ρcosθ, y=ρsinθ",
        "常见曲线的极坐标方程（圆、直线、玫瑰线）"
      ],
      "prerequisites": ["analytic-geometry", "trigonometric-functions"],
      "leads_to": [],
      "real_world": [
        "摆线（旋轮线）——车轮上一点的轨迹用参数方程描述",
        "雷达屏幕用极坐标——距离+角度",
        "天线辐射方向图——极坐标中的曲线"
      ],
      "memory_anchors": [
        "参数方程像'同步控制'——t是时间，x和y各自随时间变化",
        "极坐标像'手电筒照射'——ρ是距离，θ是角度",
        "互化公式：x=ρcosθ, y=ρsinθ, ρ²=x²+y², tanθ=y/x"
      ],
      "bloom_verbs": {
        "remember": "写出直角坐标与极坐标的互化公式",
        "understand": "解释参数方程的几何意义",
        "apply": "将椭圆的参数方程化为普通方程",
        "analyze": "用参数方程求曲线的交点",
        "evaluate": "判断用参数方程还是普通方程更方便解题",
        "create": "用参数方程描述一个运动轨迹"
      }
    },
    {
      "id": "mathematical-induction",
      "name": "数学归纳法",
      "name_en": "Mathematical Induction",
      "grade": "11",
      "semester": "上",
      "unit": "选择性必修二 第4章",
      "definition": "一种证明与正整数相关的数学命题的方法，包含归纳奠基和归纳递推两个步骤",
      "key_concepts": [
        "数学归纳法的两个步骤：奠基（验证n=1成立）+递推（假设n=k成立推n=k+1成立）",
        "归纳假设的使用：必须在证明n=k+1时用到n=k的假设",
        "常见应用：证明数列求和公式、整除问题、不等式",
        "第二数学归纳法（强归纳法）的概念"
      ],
      "prerequisites": ["sequences"],
      "leads_to": [],
      "real_world": [
        "多米诺骨牌——第一块倒了（奠基），每块能推倒下一块（递推），所以全部倒",
        "证明1+2+3+...+n=n(n+1)/2",
        "证明n!>2ⁿ（n足够大时）"
      ],
      "memory_anchors": [
        "数学归纳法就是'多米诺骨牌原理'——推倒第一块+每块能推倒下一块=全部倒下",
        "两步口诀：'一验二推'——先验n=1，再由k推k+1",
        "关键：推k+1时一定要用到k的假设——否则不算归纳法"
      ],
      "bloom_verbs": {
        "remember": "说出数学归纳法的两个步骤",
        "understand": "解释为什么两个步骤缺一不可",
        "apply": "用数学归纳法证明1²+2²+...+n²=n(n+1)(2n+1)/6",
        "analyze": "指出一个归纳法证明中的逻辑漏洞",
        "evaluate": "判断一个归纳法证明是否完整正确",
        "create": "构造一个适合用数学归纳法证明的命题"
      }
    }
  ],
  "edges": [
    { "from": "sets-logic", "to": "functions-advanced", "type": "prerequisite", "note": "集合是函数定义的基础语言" },
    { "from": "sets-logic", "to": "inequalities-advanced", "type": "prerequisite", "note": "不等式解集用集合表示" },
    { "from": "functions-advanced", "to": "trigonometric-functions", "type": "prerequisite", "note": "三角函数是函数概念的延伸" },
    { "from": "trigonometric-functions", "to": "trigonometry-solution", "type": "prerequisite", "note": "解三角形需要三角函数知识" },
    { "from": "functions-advanced", "to": "sequences", "type": "prerequisite", "note": "数列是特殊的函数" },
    { "from": "functions-advanced", "to": "derivatives", "type": "prerequisite", "note": "导数是研究函数性质的工具" },
    { "from": "trigonometric-functions", "to": "derivatives", "type": "prerequisite", "note": "三角函数的求导" },
    { "from": "sequences", "to": "derivatives", "type": "parallel", "note": "数列极限引入导数概念" },
    { "from": "inequalities-advanced", "to": "linear-programming", "type": "prerequisite", "note": "线性规划基于不等式" },
    { "from": "trigonometric-functions", "to": "vectors", "type": "prerequisite", "note": "向量夹角需要三角函数" },
    { "from": "solid-geometry", "to": "vectors", "type": "parallel", "note": "空间向量是解立体几何的工具" },
    { "from": "vectors", "to": "analytic-geometry", "type": "prerequisite", "note": "解析几何中用到向量运算" },
    { "from": "functions-advanced", "to": "analytic-geometry", "type": "prerequisite", "note": "曲线方程本质是函数关系" },
    { "from": "functions-advanced", "to": "statistics-probability-senior", "type": "prerequisite", "note": "概率分布涉及函数概念" },
    { "from": "vectors", "to": "complex-numbers", "type": "prerequisite", "note": "复数可用向量表示" },
    { "from": "analytic-geometry", "to": "parametric-polar", "type": "prerequisite", "note": "圆锥曲线是参数方程的基础" },
    { "from": "trigonometric-functions", "to": "parametric-polar", "type": "prerequisite", "note": "极坐标中大量使用三角函数" },
    { "from": "sequences", "to": "mathematical-induction", "type": "prerequisite", "note": "数列求和公式是归纳法的典型应用对象" }
  ]
}
