{
  "subject": "physics",
  "domain": "electromagnetism",
  "version": "1.0",
  "curriculum": "人教版",
  "nodes": [
    {
      "id": "circuit-basics",
      "name": "电路基础",
      "name_en": "Circuit Basics",
      "grade": "9",
      "semester": "上",
      "unit": "第15章 电流和电路",
      "definition": "电荷的定向移动形成电流，电路由电源、导线、开关和用电器组成",
      "key_concepts": [
        "电荷：正电荷、负电荷、电荷守恒",
        "电流方向：正电荷定向移动的方向",
        "串联电路与并联电路",
        "电路图的画法和识读"
      ],
      "prerequisites": [],
      "leads_to": [
        "ohms-law",
        "electric-power"
      ],
      "real_world": [
        "家里的灯泡和开关——并联电路",
        "节日彩灯串——串联电路",
        "手电筒电路——最简单的串联"
      ],
      "memory_anchors": [
        "电流像水流：电源是水泵，导线是水管，用电器是水轮",
        "串联像「糖葫芦」——一条路，一个断全断；并联像「分岔路」——各走各的互不影响"
      ],
      "bloom_verbs": {
        "remember": "说出电路的四个基本组成部分",
        "understand": "解释串联和并联电路的特点",
        "apply": "画出简单电路图",
        "analyze": "判断实际电路是串联还是并联",
        "evaluate": "诊断电路中断路和短路的原因",
        "create": "设计一个包含串并联的实用电路"
      },
      "curriculum_standards": {
        "source": "《义务教育物理课程标准（2022年版）》第四学段· 电和磁",
        "content_requirements": [
          "① 从能量转化的角度认识电源和用电器的作用。",
          "② 知道电压、电流和电阻；探究电流与电压、电阻的关系，理解欧姆定律 I=U/R。",
          "③ 会使用电流表和电压表测量电路中的电流和电压。",
          "④ 会看、会画简单的电路图；会连接简单的串联电路和并联电路。"
        ],
        "key_points": [
          "I = U/R",
          "串联:I相等,U相加; 并联:U相等,I相加"
        ],
        "teaching_tips": [
          "用水流类比电流——水压→电压，水管阻力→电阻",
          "通过实物连接练习培养动手能力",
          "强调安全用电意识"
        ]
      }
    },
    {
      "id": "ohms-law",
      "name": "欧姆定律",
      "name_en": "Ohm's Law",
      "grade": "9",
      "semester": "上",
      "unit": "第17章 欧姆定律",
      "definition": "导体中的电流与导体两端的电压成正比，与导体的电阻成反比：I=U/R",
      "key_concepts": [
        "电压U：推动电荷移动的「动力」，单位伏特(V)",
        "电阻R：导体对电流的阻碍作用，单位欧姆(Ω)",
        "欧姆定律：I=U/R",
        "串联分压、并联分流",
        "电阻的影响因素：材料、长度、横截面积、温度"
      ],
      "prerequisites": [
        "circuit-basics"
      ],
      "leads_to": [
        "electric-power",
        "electrostatics"
      ],
      "real_world": [
        "家用电器标注220V——额定电压",
        "导线越细电阻越大——横截面积影响电阻",
        "变阻器调节音量大小——改变电阻改变电流"
      ],
      "memory_anchors": [
        "I=U/R：电压是「推力」，电阻是「阻力」，推力大了电流就大，阻力大了电流就小",
        "串联分压像「串糖葫芦分糖」——电阻大分的电压多",
        "并联分流像「分岔河」——电阻小的那条路水流大"
      ],
      "bloom_verbs": {
        "remember": "写出欧姆定律公式",
        "understand": "解释电阻的物理含义",
        "apply": "用欧姆定律计算电路中的电流电压",
        "analyze": "分析串并联电路中的电压电流分配",
        "evaluate": "判断电路设计是否合理",
        "create": "设计伏安法测电阻的实验"
      },
      "curriculum_standards": [
        {
          "category": "curriculum_requirement",
          "source": "义务教育课程标准2022年版",
          "content": "理。知道内能的利用在人类社会发展\n史中的重要意义。\n例 2 了解热机对社会发展所起的作用和对环境的影响。\n活动建议:\n(1) 调查当地近年来炊事、取暖、交通等方面燃料结构的变化，\n从经济与环保的角度开展讨论。\n(2) 燃料的种类很多，如木业、煤、汽油、酒精、天然气等，查\n## 第31页\n阅资料并比较相同质量的不同燃料完全燃烧时放出热量的多少。\n3. 4 电磁能\n3.4.1 从能量转化的角度认识电源和用电器的作用。\n例 1 定性说明电热水壹、电风扇工作时能量转化的情况。\n3.4.2 知道电压、电流和电阻。探究电流与电压、电阻的关系，\n理解欧姆定律。\n3.4.3 会使用电流表和电压表。\n3.4.4 会看、会画简单的电路图。会连接简单的串联电路和并\n联电路。能说出生产生活中采用简单串联电路或并联电路的实例。探\n究并了解串联电路和并联电路中电流、电压的特点。\n3.4.5 结合实例，了解电功和电功率。知道用电器的额定功率\n和实际功率。\n例 2 调查常见用电器的铭牌，比较它们的电功率。\n3.4.6 通过实验，了解焦耳定律。能用焦耳定律说明生产生活\n中的有关现象。\n3.4.7 了解家庭电路的组成。有安全用电和节约用电的意识。\n例 3 了解我国家庭用电的电压和频率，在家庭用电中有保护自\n己和他人的安全意识。\n活动建议:\nCL) 学读家用电能表，根据读数计算用电量。\n(2) 调查当地人均用电量的变化"
        }
      ]
    },
    {
      "id": "electric-power",
      "name": "电功与电功率",
      "name_en": "Electric Power",
      "grade": "9",
      "semester": "下",
      "unit": "第18章 电功率",
      "definition": "电功是电流做的功（W=UIt），电功率是电流做功的快慢（P=UI），是衡量用电器性能的重要指标",
      "key_concepts": [
        "电功：W=UIt=Pt，单位焦耳(J)和千瓦时(kWh)",
        "电功率：P=UI=I²R=U²/R",
        "额定功率与实际功率",
        "焦耳定律：Q=I²Rt",
        "安全用电：触电、短路、过载"
      ],
      "prerequisites": [
        "circuit-basics",
        "ohms-law"
      ],
      "leads_to": [
        "electrostatics"
      ],
      "real_world": [
        "电费计算：1度=1千瓦时=3.6×10⁶J",
        "电饭锅额定功率800W——1小时用0.8度电",
        "保险丝——焦耳定律的应用"
      ],
      "memory_anchors": [
        "P=UI：功率=电压×电流——两个都大功率才大",
        "焦耳定律Q=I²Rt：发热跟电流平方成正比——电流翻倍发热翻4倍",
        "1度电=1千瓦时：1000瓦用1小时"
      ],
      "bloom_verbs": {
        "remember": "写出电功率的计算公式",
        "understand": "解释额定功率和实际功率的区别",
        "apply": "计算家用电器的耗电量",
        "analyze": "分析电路中的功率分配",
        "evaluate": "判断用电是否安全",
        "create": "设计测量小灯泡电功率的实验"
      },
      "curriculum_standards": [
        {
          "source_field": "real_world",
          "category": "required_experiment",
          "content": "2022课标必做实验：测量小灯泡的电功率——伏安法的进阶应用"
        },
        {
          "source_field": "real_world",
          "category": "cross_disciplinary",
          "content": "2022课标跨学科实践：调查家庭电路与安全用电——将电学知识与日常生活安全结合"
        }
      ]
    },
    {
      "id": "electrostatics",
      "name": "静电场",
      "name_en": "Electrostatics",
      "grade": "10",
      "semester": "下",
      "unit": "必修三 第9-10章",
      "definition": "静止电荷周围存在电场，电场对其中的电荷施加力（库仑力），电荷在电场中移动做功与电势差有关",
      "key_concepts": [
        "库仑定律：F=kq₁q₂/r²",
        "电场强度：E=F/q，方向为正电荷受力方向",
        "电势与电势差",
        "电场线和等势面",
        "电容器：C=Q/U"
      ],
      "prerequisites": [
        "ohms-law",
        "electric-power"
      ],
      "leads_to": [
        "dc-circuits",
        "magnetic-field"
      ],
      "real_world": [
        "冬天脱毛衣「触电」——静电放电",
        "复印机——静电吸附",
        "闪电——大气中的静电放电"
      ],
      "memory_anchors": [
        "库仑定律和万有引力形式一样：F=kq₁q₂/r²——只是把质量换成了电荷",
        "电场线从正到负——像「正电荷射出的箭」",
        "电容器像「蓄水池」：电压是水位，电容是池子大小"
      ],
      "bloom_verbs": {
        "remember": "写出库仑定律和电场强度公式",
        "understand": "解释电场线的含义",
        "apply": "计算点电荷间的库仑力",
        "analyze": "分析电荷在电场中的运动",
        "evaluate": "判断电场线画法是否正确",
        "create": "设计探究平行板电容器特性的方案"
      },
      "curriculum_standards": {
        "source": "《义务教育物理课程标准（2022年版）》第四学段· 电和磁",
        "content_requirements": [
          "知道摩擦起电现象；了解电荷间的相互作用规律。",
          "了解电场的基本概念（定性）。"
        ]
      }
    },
    {
      "id": "dc-circuits",
      "name": "恒定电流",
      "name_en": "DC Circuits",
      "grade": "11",
      "semester": "上",
      "unit": "必修三 第11章",
      "definition": "在闭合回路中，电源提供电动势维持电流，遵循欧姆定律和基尔霍夫定律",
      "key_concepts": [
        "电动势：电源将其他能量转化为电能的本领",
        "闭合电路欧姆定律：I=ε/(R+r)",
        "路端电压：U=ε-Ir",
        "电流表和电压表的电路连接",
        "多用电表的使用"
      ],
      "prerequisites": [
        "electrostatics"
      ],
      "leads_to": [
        "magnetic-field"
      ],
      "real_world": [
        "电池用久了电压下降——内阻增大",
        "给手机充电——电源电动势",
        "万用表测量电阻"
      ],
      "memory_anchors": [
        "闭合欧姆定律：电动势=外电压+内电压——总共这么多钱，外面花了剩下的给内阻",
        "电流表串联（像水表装在管子里），电压表并联（像量血压绑在胳膊上）"
      ],
      "bloom_verbs": {
        "remember": "写出闭合电路欧姆定律",
        "understand": "解释电动势与路端电压的关系",
        "apply": "计算闭合电路中的电流和电压",
        "analyze": "分析外电阻变化对路端电压的影响",
        "evaluate": "判断电路测量方案的误差",
        "create": "设计测量电源电动势和内阻的实验"
      },
      "curriculum_standards": {
        "source": "《义务教育物理课程标准（2022年版）》第四学段· 电和磁",
        "content_requirements": [
          "了解串联电路和并联电路的特点；知道电流表、电压表的使用方法。",
          "了解家庭电路的组成和安全用电常识。"
        ]
      }
    },
    {
      "id": "magnetic-field",
      "name": "磁场与电磁感应",
      "name_en": "Magnetic Field and Electromagnetic Induction",
      "grade": "11",
      "semester": "上",
      "unit": "选择性必修二",
      "definition": "运动电荷和电流周围存在磁场，变化的磁场产生电场（电磁感应），这是发电机和变压器的原理",
      "key_concepts": [
        "磁场：安培力F=BIL，洛伦兹力f=qvB",
        "电磁感应：法拉第定律ε=ΔΦ/Δt",
        "楞次定律：感应电流方向阻碍磁通量变化",
        "变压器原理：U₁/U₂=n₁/n₂",
        "交变电流：有效值与最大值"
      ],
      "prerequisites": [
        "electrostatics",
        "dc-circuits"
      ],
      "leads_to": [],
      "real_world": [
        "发电机——电磁感应发电",
        "变压器——远距离输电升压降压",
        "磁悬浮列车——磁力应用"
      ],
      "memory_anchors": [
        "楞次定律一句话：感应电流总是「对着干」——磁通量增就减，减就增",
        "左手安培力、右手感应电流——左力右电",
        "变压器口诀：匝多压高匝少压低——线圈越多电压越高"
      ],
      "bloom_verbs": {
        "remember": "写出法拉第电磁感应定律",
        "understand": "解释楞次定律的物理含义",
        "apply": "计算感应电动势和感应电流",
        "analyze": "分析导体切割磁力线的运动",
        "evaluate": "判断感应电流的方向",
        "create": "设计一个简单的发电机模型"
      },
      "curriculum_standards": {
        "source": "《义务教育物理课程标准（2022年版）》第四学段· 电和磁",
        "content_requirements": [
          "① 通过实验认识磁场；知道磁感线的意义；了解地磁场。",
          "② 电流周围存在磁场；探究通电螺线管外部磁场的方向。",
          "③ 了解电磁感应现象；了解发电机的工作原理。",
          "④ 了解电动机的工作原理；知道电能可以转化为机械能。"
        ],
        "teaching_tips": [
          "用铁屑演示磁感线分布",
          "对比发电机和电动机的能量转化方向",
          "结合我国北斗卫星导航系统讨论电磁技术应用"
        ]
      }
    },
    {
      "id": "alternating-current",
      "name": "交变电流",
      "name_en": "Alternating Current",
      "grade": "11",
      "semester": "下",
      "unit": "选择性必修二 第5章",
      "definition": "大小和方向随时间做周期性变化的电流叫交变电流，交流发电机利用电磁感应产生交变电流",
      "key_concepts": [
        "交变电流的产生：矩形线圈在匀强磁场中匀速转动",
        "交变电流的瞬时值：e=NBSωsin(ωt)，峰值eₘ=NBSω",
        "有效值：使交流和直流产生相同热效应，U有效=Uₘ/√2",
        "变压器原理：U₁/U₂=n₁/n₂，功率不变P₁=P₂",
        "远距离输电：高压输电减少损耗，P损=I²R线"
      ],
      "prerequisites": [
        "magnetic-field"
      ],
      "leads_to": [],
      "real_world": [
        "家用220V是交流电的有效值，峰值约311V",
        "电网变压器：发电厂升压到几十万伏输电，再逐级降到220V",
        "充电器里的变压器——把220V降到手机需要的5V"
      ],
      "memory_anchors": [
        "交流像'正弦心电图'——大小方向都在周期性变化",
        "有效值是'打折后的价格'——交流电的有效值=峰值除以根号2",
        "远距离输电口诀：升压降流省损耗——P损=I²R，电流小了损耗就小"
      ],
      "bloom_verbs": {
        "remember": "写出交变电流瞬时值和有效值的公式",
        "understand": "解释为什么用高压输电能减少损耗",
        "apply": "计算变压器原副线圈的电压电流关系",
        "analyze": "分析远距离输电中电压和电流的变化",
        "evaluate": "判断一个输电方案是否合理",
        "create": "设计一套从发电厂到用户的输变电方案"
      },
      "curriculum_standards": {
        "source": "《义务教育物理课程标准（2022年版）》拓展",
        "content_requirements": [
          "了解交流电的基本概念；知道我国家庭电路的电压（220V）和频率（50Hz）。",
          "了解变压器的作用原理（定性）。"
        ]
      }
    }
  ],
  "edges": [
    {
      "from": "circuit-basics",
      "to": "ohms-law",
      "type": "prerequisite",
      "note": "电路基础是欧姆定律的前提"
    },
    {
      "from": "circuit-basics",
      "to": "electric-power",
      "type": "prerequisite",
      "note": "理解电路才能学电功率"
    },
    {
      "from": "ohms-law",
      "to": "electric-power",
      "type": "prerequisite",
      "note": "欧姆定律是功率计算的基础"
    },
    {
      "from": "ohms-law",
      "to": "electrostatics",
      "type": "prerequisite",
      "note": "初中欧姆定律是高中电学的基础"
    },
    {
      "from": "electric-power",
      "to": "electrostatics",
      "type": "prerequisite",
      "note": "电功率概念用于高中电学"
    },
    {
      "from": "electrostatics",
      "to": "dc-circuits",
      "type": "prerequisite",
      "note": "静电场是恒定电流的基础"
    },
    {
      "from": "electrostatics",
      "to": "magnetic-field",
      "type": "prerequisite",
      "note": "电场概念是磁场学习的基础"
    },
    {
      "from": "dc-circuits",
      "to": "magnetic-field",
      "type": "prerequisite",
      "note": "电路知识是电磁感应的基础"
    },
    {
      "from": "magnetic-field",
      "to": "alternating-current",
      "type": "prerequisite",
      "note": "电磁感应是交变电流产生的原理基础"
    },
    {
      "from": "dc-circuits",
      "to": "alternating-current",
      "type": "prerequisite",
      "note": "直流电路知识是理解交流电路的基础"
    }
  ]
}