[
  {
    "id": "err-num10-compare-sign",
    "node_id": "numbers-within-10",
    "grade": "1",
    "type": "conceptual",
    "description": "混淆>和<符号方向，将大于号和小于号用反",
    "wrong_answer": "3 > 5",
    "correct_answer": "3 < 5",
    "diagnosis": "大于号开口朝大数，小于号尖角对小数。口诀：开口对大数，尖角对小数。",
    "frequency": "high",
    "trigger": ">和<符号方向记忆混淆"
  },
  {
    "id": "err-num10-zero-meaning",
    "node_id": "numbers-within-10",
    "grade": "1",
    "type": "conceptual",
    "description": "认为0不是数或0不能参与比较",
    "wrong_answer": "0不是一个数",
    "correct_answer": "0是最小的自然数，表示一个也没有",
    "diagnosis": "0是有意义的数，它表示'一个也没有'，是最小的自然数，可以参与大小比较。",
    "frequency": "medium",
    "trigger": "对0的数学含义理解不足"
  },
  {
    "id": "err-add20-split-error",
    "node_id": "addition-subtraction-within-20",
    "grade": "1",
    "type": "procedural",
    "description": "凑十法拆数错误，如9+6把6拆成1和6",
    "wrong_answer": "9+6→9+1+6=16",
    "correct_answer": "9+6→把6拆成1和5→9+1=10→10+5=15",
    "diagnosis": "凑十法关键：拆小数凑大数到10。9需要1来凑十，所以把6拆成1+5，先算9+1=10，再10+5=15。",
    "frequency": "high",
    "trigger": "凑十法拆数步骤出错"
  },
  {
    "id": "err-add20-break-ten",
    "node_id": "addition-subtraction-within-20",
    "grade": "1",
    "type": "procedural",
    "description": "破十法时拆错数，如13-5拆成13-3-3=7",
    "wrong_answer": "13-5=7（错把5拆成3和3）",
    "correct_answer": "13-5=8（先13-3=10，再10-2=8，5拆成3和2）",
    "diagnosis": "破十法第一步先减到10（13-3=10），所以5要拆成3和2，再算10-2=8。",
    "frequency": "high",
    "trigger": "破十法拆数配对错误"
  },
  {
    "id": "err-num100-place-value",
    "node_id": "numbers-within-100",
    "grade": "1",
    "type": "conceptual",
    "description": "混淆十位和个位含义，如35中3表示3个一",
    "wrong_answer": "35中的3表示3个一",
    "correct_answer": "35中的3在十位，表示3个十（30）",
    "diagnosis": "位值原理：同一个数字在不同数位表示不同的值。十位上的3=3个十=30，个位上的5=5个一=5。",
    "frequency": "high",
    "trigger": "位值概念未建立"
  },
  {
    "id": "err-add100-carry-lost",
    "node_id": "addition-subtraction-within-100",
    "grade": "1-2",
    "type": "procedural",
    "description": "进位加法忘记向十位进1",
    "wrong_answer": "47+38=75（个位7+8=15写5，忘进1）",
    "correct_answer": "47+38=85（个位15写5进1，十位4+3+1=8）",
    "diagnosis": "竖式加法个位满十必须向十位进1。建议在十位上方标注小小的进位'1'。",
    "frequency": "high",
    "trigger": "进位标记遗漏"
  },
  {
    "id": "err-add100-borrow-reverse",
    "node_id": "addition-subtraction-within-100",
    "grade": "1-2",
    "type": "procedural",
    "description": "退位减法个位不够减时反过来用大数减小数",
    "wrong_answer": "52-37=25（个位2不够减7，写7-2=5）",
    "correct_answer": "52-37=15（借1后个位12-7=5，十位5-1-3=1）",
    "diagnosis": "个位不够减要向十位借1当10，不能反过来用大减小。2不够减7→借1变成12→12-7=5。",
    "frequency": "high",
    "trigger": "退位规则不理解，直接大减小"
  },
  {
    "id": "err-mult-table-67",
    "node_id": "multiplication-table",
    "grade": "2",
    "type": "careless",
    "description": "相邻口诀混淆，如六七四十二记成四十三",
    "wrong_answer": "6×7=43",
    "correct_answer": "6×7=42",
    "diagnosis": "六七四十二是最易混口诀。验证法：6×7=6×6+6=36+6=42。",
    "frequency": "high",
    "trigger": "口诀记忆不牢"
  },
  {
    "id": "err-mult-add-confuse",
    "node_id": "multiplication-table",
    "grade": "2",
    "type": "conceptual",
    "description": "将乘法理解为加法，3×4算成3+4",
    "wrong_answer": "每排4个苹果3排共3+4=7个",
    "correct_answer": "3排每排4个=3×4=12个（3个4相加）",
    "diagnosis": "乘法是'几个几相加'的简写。3×4=4+4+4=12，不是3+4=7。",
    "frequency": "medium",
    "trigger": "乘法与加法含义混淆"
  },
  {
    "id": "err-div-remainder-big",
    "node_id": "division-concept",
    "grade": "2",
    "type": "procedural",
    "description": "有余数除法中余数≥除数",
    "wrong_answer": "17÷5=2……7",
    "correct_answer": "17÷5=3……2（余数2<除数5）",
    "diagnosis": "余数必须小于除数。如果余数≥除数，说明商还可以再大1。",
    "frequency": "high",
    "trigger": "余数<除数规则遗忘"
  },
  {
    "id": "err-num10000-read-zero",
    "node_id": "numbers-within-10000",
    "grade": "2",
    "type": "procedural",
    "description": "中间有0的数读法错误，多读零或漏读零",
    "wrong_answer": "6050读作六千零五零",
    "correct_answer": "6050读作六千零五十（中间连续0只读一个零，末尾0不读）",
    "diagnosis": "读数规则：中间不管几个连续0只读一个零，末尾的0不读。",
    "frequency": "high",
    "trigger": "含0读数规则不清"
  },
  {
    "id": "err-multidigit-continuous-carry",
    "node_id": "multi-digit-addition-subtraction",
    "grade": "3",
    "type": "procedural",
    "description": "连续进位时漏掉某一位的进位",
    "wrong_answer": "568+275=733（十位忘进位）",
    "correct_answer": "568+275=843（个位13进1，十位14进1，百位8）",
    "diagnosis": "连续进位像多米诺骨牌，每位满十都要进。建议每位标清进位标记。",
    "frequency": "high",
    "trigger": "连续进位某位遗漏"
  },
  {
    "id": "err-multidigit-borrow-zero",
    "node_id": "multi-digit-addition-subtraction",
    "grade": "3",
    "type": "procedural",
    "description": "隔位退位中间0位无法借时处理错误",
    "wrong_answer": "1000-456=654",
    "correct_answer": "1000-456=544",
    "diagnosis": "1000-456需从千位逐步退位：千位退1→百位变10退1→十位变10退1→个位变10。",
    "frequency": "high",
    "trigger": "中间有0的退位处理不当"
  },
  {
    "id": "err-mult-shift",
    "node_id": "multi-digit-multiplication",
    "grade": "3-4",
    "type": "procedural",
    "description": "两位数乘两位数竖式第二层没左移一位",
    "wrong_answer": "23×45→115+92=207",
    "correct_answer": "23×45→115+920=1035（第二层左移一位）",
    "diagnosis": "第二层乘的是十位上的数，实际是×40，所以要左移一位（相当于末尾补0）。",
    "frequency": "high",
    "trigger": "错位相加原理不理解"
  },
  {
    "id": "err-div-quotient-zero",
    "node_id": "multi-digit-division",
    "grade": "3-4",
    "type": "procedural",
    "description": "商中间需要写0占位却跳过",
    "wrong_answer": "612÷6=12（跳过十位）",
    "correct_answer": "612÷6=102（十位1÷6不够商0）",
    "diagnosis": "除到哪位不够除就在那位上商0占位，不能跳过。口诀：不够除，商零占。",
    "frequency": "high",
    "trigger": "商中间0遗漏"
  },
  {
    "id": "err-law-distribute-minus",
    "node_id": "operations-laws",
    "grade": "4",
    "type": "procedural",
    "description": "分配律遇减号时只分配给第一项",
    "wrong_answer": "25×(40-4)=25×40-4=996",
    "correct_answer": "25×(40-4)=25×40-25×4=1000-100=900",
    "diagnosis": "分配律对括号里每一项都要乘。a×(b-c)=a×b-a×c，不能只乘第一项。",
    "frequency": "high",
    "trigger": "分配律减法情形分配不完整"
  },
  {
    "id": "err-frac-unequal-parts",
    "node_id": "fraction-concept",
    "grade": "3-5",
    "type": "conceptual",
    "description": "不平均分也用分数表示",
    "wrong_answer": "蛋糕切成大小不等的两块，每块是1/2",
    "correct_answer": "只有平均分成两份，每份才是1/2",
    "diagnosis": "分数的前提是'平均分'。大小不等的两块不能叫1/2。",
    "frequency": "high",
    "trigger": "忽视平均分的前提"
  },
  {
    "id": "err-frac-add-denom",
    "node_id": "fraction-operations",
    "grade": "5-6",
    "type": "procedural",
    "description": "异分母分数相加时分子分母都直接相加",
    "wrong_answer": "1/3+1/4=2/7",
    "correct_answer": "1/3+1/4=4/12+3/12=7/12",
    "diagnosis": "异分母分数不能直接加，要先通分再分子相加。1/3=4/12，1/4=3/12。",
    "frequency": "high",
    "trigger": "异分母直接相加"
  },
  {
    "id": "err-frac-div-reciprocal",
    "node_id": "fraction-operations",
    "grade": "5-6",
    "type": "procedural",
    "description": "分数除法忘取倒数",
    "wrong_answer": "2/3÷1/4→分子÷分子分母÷分母",
    "correct_answer": "2/3÷1/4=2/3×4/1=8/3",
    "diagnosis": "分数除法=乘以除数的倒数。'翻跟头'：÷1/4变成×4/1。",
    "frequency": "high",
    "trigger": "忘记取倒数"
  },
  {
    "id": "err-decimal-read-integer",
    "node_id": "decimal-concept",
    "grade": "3-4",
    "type": "procedural",
    "description": "小数部分按整数方式读",
    "wrong_answer": "0.56读作零点五十六",
    "correct_answer": "0.56读作零点五六（逐位读）",
    "diagnosis": "小数部分必须逐位读出每个数字，不按整数读。0.56读'零点五六'。",
    "frequency": "medium",
    "trigger": "小数读法与整数混淆"
  },
  {
    "id": "err-decimal-point-align",
    "node_id": "decimal-operations",
    "grade": "4-5",
    "type": "procedural",
    "description": "小数加减按末位对齐而非小数点对齐",
    "wrong_answer": "12.5+3.45末位对齐导致算错",
    "correct_answer": "小数加减必须小数点对齐：12.50+3.45=15.95",
    "diagnosis": "小数加减铁律：小数点对齐。位数不同可末尾补0。",
    "frequency": "high",
    "trigger": "对齐方式错误"
  },
  {
    "id": "err-decimal-mult-count",
    "node_id": "decimal-operations",
    "grade": "4-5",
    "type": "procedural",
    "description": "小数乘法积的小数位数数错",
    "wrong_answer": "3.6×2.5=90（少点了一位小数）",
    "correct_answer": "3.6×2.5=9.00=9（因数共2位小数）",
    "diagnosis": "两个因数的小数位数之和=积的小数位数。1位+1位=2位，900→9.00=9。",
    "frequency": "high",
    "trigger": "小数位数求和规则出错"
  },
  {
    "id": "err-ratio-simplify-value",
    "node_id": "ratio-proportion",
    "grade": "6",
    "type": "conceptual",
    "description": "混淆化简比和求比值",
    "wrong_answer": "12:8化简为1.5",
    "correct_answer": "化简比12:8=3:2；求比值12÷8=1.5",
    "diagnosis": "化简比结果是最简整数比（3:2），求比值结果是一个数（1.5）。两者不同。",
    "frequency": "high",
    "trigger": "两个概念混淆"
  },
  {
    "id": "err-ratio-direct-inverse",
    "node_id": "ratio-proportion",
    "grade": "6",
    "type": "conceptual",
    "description": "混淆正反比例，将速度和时间判断为正比例",
    "wrong_answer": "路程一定时速度和时间成正比例",
    "correct_answer": "速度×时间=路程（定值），成反比例",
    "diagnosis": "正比例：y/x=k。反比例：xy=k。速度快时间短是反向变化=反比例。",
    "frequency": "high",
    "trigger": "正反比例判断混淆"
  },
  {
    "id": "err-large-num-rewrite",
    "node_id": "large-numbers",
    "grade": "4",
    "type": "procedural",
    "description": "大数改写以万为单位时去0个数错",
    "wrong_answer": "35600000=356万",
    "correct_answer": "35600000=3560万",
    "diagnosis": "改写以万为单位：从右数第5位开始是万位。35600000→3560|0000→3560万。",
    "frequency": "high",
    "trigger": "万位位置找错"
  },
  {
    "id": "err-negative-compare",
    "node_id": "negative-numbers",
    "grade": "6",
    "type": "conceptual",
    "description": "负数比较时认为绝对值大的更大",
    "wrong_answer": "-5>-2",
    "correct_answer": "-5<-2（负数绝对值越大越小）",
    "diagnosis": "负数比较和正数相反：数轴上越靠左越小。-5在-2左边所以-5<-2。",
    "frequency": "high",
    "trigger": "负数大小规律与正数混淆"
  },
  {
    "id": "err-negative-zero",
    "node_id": "negative-numbers",
    "grade": "6",
    "type": "conceptual",
    "description": "将0归为正数或负数",
    "wrong_answer": "0是正数",
    "correct_answer": "0既不是正数也不是负数",
    "diagnosis": "0是正负数的分界点，它既不是正数也不是负数。",
    "frequency": "medium",
    "trigger": "0的分类记忆错误"
  }
]
